[{"KR2ID":"K0902221","KR_Tenri_p":"Tc176210","KR_vol_name":"僧中","KR_radical":"缶","KR_vol":"v9","KR_radical_num":94,"Entry":"缶","Def":"俗⿳𠂉二山　クマ(HH)　ー歟","KRID_sn":"S34254","KRID":"K09022210"},{"KR2ID":"K0902222","KR_Tenri_p":"Tc176220","KR_vol_name":"僧中","KR_radical":"缶","KR_vol":"v9","KR_radical_num":94,"Entry":"缻","Def":"或","KRID_sn":"S34255","KRID":"K09022220"},{"KR2ID":"K0902223","KR_Tenri_p":"Tc176230","KR_vol_name":"僧中","KR_radical":"缶","KR_vol":"v9","KR_radical_num":94,"Entry":"𦈢","Def":"俗歟","KRID_sn":"S34256","KRID":"K09022230"},{"KR2ID":"K0902224","KR_Tenri_p":"Tc176240","KR_vol_name":"僧中","KR_radical":"缶","KR_vol":"v9","KR_radical_num":94,"Entry":"缶","Def":"音不　ホトキ　マタシ(HH@)　又甫之反","KRID_sn":"S34257","KRID":"K09022240"},{"KR2ID":"K0902231","KR_Tenri_p":"Tc176310","KR_vol_name":"僧中","KR_radical":"缶","KR_vol":"v9","KR_radical_num":94,"Entry":"𦈢","Def":"俗非","KRID_sn":"S34258","KRID":"K09022310"},{"KR2ID":"K0902232","KR_Tenri_p":"Tc176320","KR_vol_name":"僧中","KR_radical":"缶","KR_vol":"v9","KR_radical_num":94,"Entry":"罌","Def":"今甖　乙莖反　瓦器","KRID_sn":"S34259","KRID":"K09022320"},{"KR2ID":"K0902233","KR_Tenri_p":"Tc176330","KR_vol_name":"僧中","KR_radical":"缶","KR_vol":"v9","KR_radical_num":94,"Entry":"䍌","Def":"或⿰立瓦　蒲侯反　薄原反　器","KRID_sn":"S34260","KRID":"K09022330"},{"KR2ID":"K0902234","KR_Tenri_p":"Tc176340","KR_vol_name":"僧中","KR_radical":"缶","KR_vol":"v9","KR_radical_num":94,"Entry":"䍇","Def":"土蹋反　下正","KRID_sn":"S34261","KRID":"K09022340"},{"KR2ID":"K0902241","KR_Tenri_p":"Tc176410","KR_vol_name":"僧中","KR_radical":"缶","KR_vol":"v9","KR_radical_num":94,"Entry":"缸","Def":"今瓨　音降　缾罐之類","KRID_sn":"S34262","KRID":"K09022410"},{"KR2ID":"K0902242","KR_Tenri_p":"Tc176420","KR_vol_name":"僧中","KR_radical":"缶","KR_vol":"v9","KR_radical_num":94,"Entry":"罃","Def":"今甇　乙莖反","KRID_sn":"S34263","KRID":"K09022420"},{"KR2ID":"K0902243","KR_Tenri_p":"Tc176430","KR_vol_name":"僧中","KR_radical":"缶","KR_vol":"v9","KR_radical_num":94,"Entry":"𦈸","Def":"音域　瓦器","KRID_sn":"S34264","KRID":"K09022430"},{"KR2ID":"K0902244","KR_Tenri_p":"Tc176440","KR_vol_name":"僧中","KR_radical":"缶","KR_vol":"v9","KR_radical_num":94,"Entry":"䍎","Def":"音寸　又千見反　瓦器","KRID_sn":"S34265","KRID":"K09022440"},{"KR2ID":"K0902251","KR_Tenri_p":"Tc176511","KR_vol_name":"僧中","KR_radical":"缶","KR_vol":"v9","KR_radical_num":94,"Entry":"䍃","Def":"今正　音由　瓦罌","KRID_sn":"S34266","KRID":"K09022511"},{"KR2ID":"K0902251","KR_Tenri_p":"Tc176511","KR_vol_name":"僧中","KR_radical":"缶","KR_vol":"v9","KR_radical_num":94,"Entry":"⿱⿹勹欠缶","Def":"今正　音由　瓦罌","KRID_sn":"S34267","KRID":"K09022512"},{"KR2ID":"K0902252","KR_Tenri_p":"Tc176520","KR_vol_name":"僧中","KR_radical":"缶","KR_vol":"v9","KR_radical_num":94,"Entry":"𦉢","Def":"音零　似瓶有耳","KRID_sn":"S34268","KRID":"K09022520"},{"KR2ID":"K0902253","KR_Tenri_p":"Tc176530","KR_vol_name":"僧中","KR_radical":"缶","KR_vol":"v9","KR_radical_num":94,"Entry":"䍄","Def":"今㓠　音點　缺","KRID_sn":"S34269","KRID":"K09022530"},{"KR2ID":"K0902254","KR_Tenri_p":"Tc176540","KR_vol_name":"僧中","KR_radical":"缶","KR_vol":"v9","KR_radical_num":94,"Entry":"罅","Def":"呼嫁反　㙤𨻲〈二或〉　孔","KRID_sn":"S34270","KRID":"K09022540"},{"KR2ID":"K0902261","KR_Tenri_p":"Tc176610","KR_vol_name":"僧中","KR_radical":"缶","KR_vol":"v9","KR_radical_num":94,"Entry":"罅","Def":"俗歟　サケメ(LLL)　カケタリ(HL@@)","KRID_sn":"S34271","KRID":"K09022610"},{"KR2ID":"K0902262","KR_Tenri_p":"Tc176621","KR_vol_name":"僧中","KR_radical":"缶","KR_vol":"v9","KR_radical_num":94,"Entry":"⿰缶雽","Def":"並俗歟","KRID_sn":"S34272","KRID":"K09022621"},{"KR2ID":"K0902262","KR_Tenri_p":"Tc176621","KR_vol_name":"僧中","KR_radical":"缶","KR_vol":"v9","KR_radical_num":94,"Entry":"⿰缶⿱覀十","Def":"並俗歟","KRID_sn":"S34273","KRID":"K09022622"},{"KR2ID":"K0902263","KR_Tenri_p":"Tc176630","KR_vol_name":"僧中","KR_radical":"缶","KR_vol":"v9","KR_radical_num":94,"Entry":"⿰缶雩","Def":"俗歟　ヱメリ(HL@)　カケタリ(HL@@)","KRID_sn":"S34274","KRID":"K09022630"},{"KR2ID":"K0902264","KR_Tenri_p":"Tc176641","KR_vol_name":"僧中","KR_radical":"缶","KR_vol":"v9","KR_radical_num":94,"Entry":"罄","Def":"今正⿱殸正俗　空定反　瓦器中空　ツクル(HHL)","KRID_sn":"S34275","KRID":"K09022641"},{"KR2ID":"K0902264","KR_Tenri_p":"Tc176641","KR_vol_name":"僧中","KR_radical":"缶","KR_vol":"v9","KR_radical_num":94,"Entry":"罄","Def":"今正⿱殸正俗　空定反　瓦器中空　ツクル(HHL)","KRID_sn":"S34276","KRID":"K09022642"},{"KR2ID":"K0902272","KR_Tenri_p":"Tc176721","KR_vol_name":"僧中","KR_radical":"缶","KR_vol":"v9","KR_radical_num":94,"Entry":"⿱軗缶","Def":"今正　音契　盡","KRID_sn":"S34277","KRID":"K09022721"},{"KR2ID":"K0902272","KR_Tenri_p":"Tc176721","KR_vol_name":"僧中","KR_radical":"缶","KR_vol":"v9","KR_radical_num":94,"Entry":"罊","Def":"今正　音契　盡","KRID_sn":"S34278","KRID":"K09022722"},{"KR2ID":"K0902273","KR_Tenri_p":"Tc176730","KR_vol_name":"僧中","KR_radical":"缶","KR_vol":"v9","KR_radical_num":94,"Entry":"缿","Def":"音項　受錢器","KRID_sn":"S34279","KRID":"K09022730"},{"KR2ID":"K0902274","KR_Tenri_p":"Tc176741","KR_vol_name":"僧中","KR_radical":"缶","KR_vol":"v9","KR_radical_num":94,"Entry":"缺","Def":"俗正　苦穴反　𡙇〈《声類》正〉　カク　ワル(HL)","KRID_sn":"S34280","KRID":"K09022741"},{"KR2ID":"K0902274","KR_Tenri_p":"Tc176741","KR_vol_name":"僧中","KR_radical":"缶","KR_vol":"v9","KR_radical_num":94,"Entry":"缺","Def":"俗正　苦穴反　𡙇〈《声類》正〉　カク　ワル(HL)","KRID_sn":"S34281","KRID":"K09022742"},{"KR2ID":"K0902282","KR_Tenri_p":"Tc176820","KR_vol_name":"僧中","KR_radical":"缶","KR_vol":"v9","KR_radical_num":94,"Entry":"缺","Def":"同","KRID_sn":"S34282","KRID":"K09022820"},{"KR2ID":"K0902283","KR_Tenri_p":"Tc176830","KR_vol_name":"僧中","KR_radical":"缶","KR_vol":"v9","KR_radical_num":94,"Entry":"罍","Def":"正櫑壘鑘三或　音雷　酒尊　モタヒ(LLL)　力癸反","KRID_sn":"S34283","KRID":"K09022830"},{"KR2ID":"K0902311","KR_Tenri_p":"Tc177110","KR_vol_name":"僧中","KR_radical":"缶","KR_vol":"v9","KR_radical_num":94,"Entry":"䍊","Def":"音撃　吹缼","KRID_sn":"S34284","KRID":"K09023110"},{"KR2ID":"K0902312","KR_Tenri_p":"Tc177120","KR_vol_name":"僧中","KR_radical":"缶","KR_vol":"v9","KR_radical_num":94,"Entry":"𬙍","Def":"音形　㼛劍二或　酒器","KRID_sn":"S34285","KRID":"K09023120"},{"KR2ID":"K0902313","KR_Tenri_p":"Tc177130","KR_vol_name":"僧中","KR_radical":"缶","KR_vol":"v9","KR_radical_num":94,"Entry":"𦉕","Def":"或𤮜　徒丹反　器縁","KRID_sn":"S34286","KRID":"K09023130"},{"KR2ID":"K0902314","KR_Tenri_p":"Tc177140","KR_vol_name":"僧中","KR_radical":"缶","KR_vol":"v9","KR_radical_num":94,"Entry":"𦉁","Def":"或㼵　音提","KRID_sn":"S34287","KRID":"K09023140"},{"KR2ID":"K0902321","KR_Tenri_p":"Tc177210","KR_vol_name":"僧中","KR_radical":"缶","KR_vol":"v9","KR_radical_num":94,"Entry":"𦈱","Def":"今瓷　音慈　ー器","KRID_sn":"S34288","KRID":"K09023210"},{"KR2ID":"K0902322","KR_Tenri_p":"Tc177221","KR_vol_name":"僧中","KR_radical":"缶","KR_vol":"v9","KR_radical_num":94,"Entry":"㓡","Def":"撫府二音　計上共三","KRID_sn":"S34289","KRID":"K09023221"},{"KR2ID":"K0902322","KR_Tenri_p":"Tc177221","KR_vol_name":"僧中","KR_radical":"缶","KR_vol":"v9","KR_radical_num":94,"Entry":"𠛺","Def":"撫府二音　計上共三","KRID_sn":"S34290","KRID":"K09023222"},{"KR2ID":"K0902323","KR_Tenri_p":"Tc177230","KR_vol_name":"僧中","KR_radical":"缶","KR_vol":"v9","KR_radical_num":94,"Entry":"缾","Def":"蒲丁反　ツルへ(HHL\")　カメ(LL)","KRID_sn":"S34291","KRID":"K09023230"},{"KR2ID":"K0902324","KR_Tenri_p":"Tc177240","KR_vol_name":"僧中","KR_radical":"缶","KR_vol":"v9","KR_radical_num":94,"Entry":"垂","Def":"是規反","KRID_sn":"S34292","KRID":"K09023240"},{"KR2ID":"K0902331","KR_Tenri_p":"Tc177310","KR_vol_name":"僧中","KR_radical":"缶","KR_vol":"v9","KR_radical_num":94,"Entry":"罋","Def":"音雍(L)　ツルへ(HHL\")","KRID_sn":"S34293","KRID":"K09023310"},{"KR2ID":"K0902332","KR_Tenri_p":"Tc177320","KR_vol_name":"僧中","KR_radical":"缶","KR_vol":"v9","KR_radical_num":94,"Entry":"罐","Def":"音貫　ツルへ(HHL\")　ホトキ","KRID_sn":"S34294","KRID":"K09023320"},{"KR2ID":"K0902333","KR_Tenri_p":"Tc177330","KR_vol_name":"僧中","KR_radical":"缶","KR_vol":"v9","KR_radical_num":94,"Entry":"⿳⿰未攴一正","Def":"之𨛋反　又作整","KRID_sn":"S34295","KRID":"K09023330"},{"KR2ID":"K0902334","KR_Tenri_p":"Tc177340","KR_vol_name":"僧中","KR_radical":"缶","KR_vol":"v9","KR_radical_num":94,"Entry":"罇","Def":"通樽字　モタヒ(LLL)","KRID_sn":"S34296","KRID":"K09023340"},{"KR2ID":"K0902341","KR_Tenri_p":"Tc177410","KR_vol_name":"僧中","KR_radical":"缶","KR_vol":"v9","KR_radical_num":94,"Entry":"⿰缶𠁣","Def":"通⿰垂𠁣字","KRID_sn":"S34297","KRID":"K09023410"},{"KR2ID":"K0902342","KR_Tenri_p":"Tc177420","KR_vol_name":"僧中","KR_radical":"缶","KR_vol":"v9","KR_radical_num":94,"Entry":"䍆","Def":"或𤲑字","KRID_sn":"S34298","KRID":"K09023420"},{"KR2ID":"K0902343","KR_Tenri_p":"Tc177430","KR_vol_name":"僧中","KR_radical":"缶","KR_vol":"v9","KR_radical_num":94,"Entry":"⿱䜌缶","Def":"俗轡字","KRID_sn":"S34299","KRID":"K09023430"},{"KR2ID":"K0902344","KR_Tenri_p":"Tc177440","KR_vol_name":"僧中","KR_radical":"缶","KR_vol":"v9","KR_radical_num":94,"Entry":"𪔕","Def":"〈正〉⿰壹荅〈俗〉　音疼","KRID_sn":"S34300","KRID":"K09023440"}]