[{"KR2ID":"K0708711","KR_Tenri_p":"Tb381110","KR_vol_name":"法下","KR_radical":"尸","KR_vol":"v7","KR_radical_num":71,"Entry":"尸","Def":"音屍(L)　カハネ(@H\"@)　カハネサラス　ツラヌ(HH@)　ツカサトル(HH@@@)　ノリヰル　アルシ　ノス","KRID_sn":"S26357","KRID":"K07087110"},{"KR2ID":"K0708713","KR_Tenri_p":"Tb381130","KR_vol_name":"法下","KR_radical":"尸","KR_vol":"v7","KR_radical_num":71,"Entry":"尼","Def":"奴啓女飢二反　スナハチ　進也　上也　定也　スナハチ　安也　和也　ヤハラカナリ","KRID_sn":"S26358","KRID":"K07087130"},{"KR2ID":"K0708721","KR_Tenri_p":"Tb381210","KR_vol_name":"法下","KR_radical":"尸","KR_vol":"v7","KR_radical_num":71,"Entry":"𡰱","Def":"俗　アマ　和ニ(L)","KRID_sn":"S26359","KRID":"K07087210"},{"KR2ID":"K0708722","KR_Tenri_p":"Tb381221","KR_vol_name":"法下","KR_radical":"尸","KR_vol":"v7","KR_radical_num":71,"Entry":"犀","Def":"音西(L)「セイ」　此間音サイ(L@)","KRID_sn":"S26360","KRID":"K07087221"},{"KR2ID":"K0708722","KR_Tenri_p":"Tb381221","KR_vol_name":"法下","KR_radical":"尸","KR_vol":"v7","KR_radical_num":71,"Entry":"犀","Def":"音西(L)「セイ」　此間音サイ(L@)","KRID_sn":"S26361","KRID":"K07087222"},{"KR2ID":"K0708723","KR_Tenri_p":"Tb381231","KR_vol_name":"法下","KR_radical":"尸","KR_vol":"v7","KR_radical_num":71,"Entry":"屖","Def":"俗","KRID_sn":"S26362","KRID":"K07087231"},{"KR2ID":"K0708723","KR_Tenri_p":"Tb381231","KR_vol_name":"法下","KR_radical":"尸","KR_vol":"v7","KR_radical_num":71,"Entry":"⿸尸⿱水牛","Def":"俗","KRID_sn":"S26363","KRID":"K07087232"},{"KR2ID":"K0708723","KR_Tenri_p":"Tb381231","KR_vol_name":"法下","KR_radical":"尸","KR_vol":"v7","KR_radical_num":71,"Entry":"⿸尸⿱仁牛","Def":"俗","KRID_sn":"S26364","KRID":"K07087233"},{"KR2ID":"K0708723","KR_Tenri_p":"Tb381231","KR_vol_name":"法下","KR_radical":"尸","KR_vol":"v7","KR_radical_num":71,"Entry":"⿸尸⿱火干","Def":"俗","KRID_sn":"S26365","KRID":"K07087234"},{"KR2ID":"K0708724","KR_Tenri_p":"Tb381240","KR_vol_name":"法下","KR_radical":"尸","KR_vol":"v7","KR_radical_num":71,"Entry":"⿸尸⿱⿰二二十","Def":"俗歟","KRID_sn":"S26366","KRID":"K07087240"},{"KR2ID":"K0708731","KR_Tenri_p":"Tb381310","KR_vol_name":"法下","KR_radical":"尸","KR_vol":"v7","KR_radical_num":71,"Entry":"屖","Def":"音西　瓠ー爪中　サネ(LL)","KRID_sn":"S26367","KRID":"K07087310"},{"KR2ID":"K0708732","KR_Tenri_p":"Tb381320","KR_vol_name":"法下","KR_radical":"尸","KR_vol":"v7","KR_radical_num":71,"Entry":"𡱝","Def":"ツヨシ","KRID_sn":"S26368","KRID":"K07087320"},{"KR2ID":"K0708733","KR_Tenri_p":"Tb381330","KR_vol_name":"法下","KR_radical":"尸","KR_vol":"v7","KR_radical_num":71,"Entry":"羼","Def":"初産反　羊相廁　羊ノキサヤ　又去声　和セン","KRID_sn":"S26369","KRID":"K07087330"},{"KR2ID":"K0708741","KR_Tenri_p":"Tb381410","KR_vol_name":"法下","KR_radical":"尸","KR_vol":"v7","KR_radical_num":71,"Entry":"⿸尸⿻⿱人人⿱人人十","Def":"ヨロコフ","KRID_sn":"S26370","KRID":"K07087410"},{"KR2ID":"K0708742","KR_Tenri_p":"Tb381420","KR_vol_name":"法下","KR_radical":"尸","KR_vol":"v7","KR_radical_num":71,"Entry":"⿸尸⿳一口干","Def":"俗群字","KRID_sn":"S26371","KRID":"K07087420"},{"KR2ID":"K0708743","KR_Tenri_p":"Tb381430","KR_vol_name":"法下","KR_radical":"尸","KR_vol":"v7","KR_radical_num":71,"Entry":"㞟","Def":"頂亭員三音　辰","KRID_sn":"S26372","KRID":"K07087430"},{"KR2ID":"K0708744","KR_Tenri_p":"Tb381440","KR_vol_name":"法下","KR_radical":"尸","KR_vol":"v7","KR_radical_num":71,"Entry":"⿸尸⿳一曲⿰亍亍","Def":"俗","KRID_sn":"S26373","KRID":"K07087440"},{"KR2ID":"K0708751","KR_Tenri_p":"Tb381510","KR_vol_name":"法下","KR_radical":"尸","KR_vol":"v7","KR_radical_num":71,"Entry":"屨","Def":"音句　クツ(LL)　麻也　又倶遇反　フム(HL)","KRID_sn":"S26374","KRID":"K07087510"},{"KR2ID":"K07087521","KR_Tenri_p":"Tb381521","KR_vol_name":"法下","KR_radical":"尸","KR_vol":"v7","KR_radical_num":71,"Entry":"⿸尸⿰彳𡞔","Def":"正","KRID_sn":"S26375","KRID":"K07087521"},{"KR2ID":"K07087522","KR_Tenri_p":"Tb381522","KR_vol_name":"法下","KR_radical":"尸","KR_vol":"v7","KR_radical_num":71,"Entry":"⿸尸⿰丬⿱串女","Def":"俗","KRID_sn":"S26376","KRID":"K07087522"},{"KR2ID":"K0708753","KR_Tenri_p":"Tb381530","KR_vol_name":"法下","KR_radical":"尸","KR_vol":"v7","KR_radical_num":71,"Entry":"屢","Def":"力句反　ハコ　シハヽヽ(HH\"@@)　スミヤカニ(LL@@@)","KRID_sn":"S26377","KRID":"K07087530"},{"KR2ID":"K07087541","KR_Tenri_p":"Tb381541","KR_vol_name":"法下","KR_radical":"尸","KR_vol":"v7","KR_radical_num":71,"Entry":"⿸尸𡞔","Def":"正","KRID_sn":"S26378","KRID":"K07087541"},{"KR2ID":"K07087542","KR_Tenri_p":"Tb381542","KR_vol_name":"法下","KR_radical":"尸","KR_vol":"v7","KR_radical_num":71,"Entry":"⿸尸⿳中一女","Def":"俗","KRID_sn":"S26379","KRID":"K07087542"},{"KR2ID":"K0708761","KR_Tenri_p":"Tb381611","KR_vol_name":"法下","KR_radical":"尸","KR_vol":"v7","KR_radical_num":71,"Entry":"⿸尸圭","Def":"於計反","KRID_sn":"S26380","KRID":"K07087611"},{"KR2ID":"K0708761","KR_Tenri_p":"Tb381611","KR_vol_name":"法下","KR_radical":"尸","KR_vol":"v7","KR_radical_num":71,"Entry":"⿸尸湮","Def":"於計反","KRID_sn":"S26381","KRID":"K07087612"},{"KR2ID":"K0708762","KR_Tenri_p":"Tb381621","KR_vol_name":"法下","KR_radical":"尸","KR_vol":"v7","KR_radical_num":71,"Entry":"𡰸","Def":"音劇(S)「ケキ」","KRID_sn":"S26382","KRID":"K07087621"},{"KR2ID":"K0708762","KR_Tenri_p":"Tb381621","KR_vol_name":"法下","KR_radical":"尸","KR_vol":"v7","KR_radical_num":71,"Entry":"屐","Def":"音劇(S)「ケキ」","KRID_sn":"S26383","KRID":"K07087622"},{"KR2ID":"K0708763","KR_Tenri_p":"Tb381630","KR_vol_name":"法下","KR_radical":"尸","KR_vol":"v7","KR_radical_num":71,"Entry":"⿸尸技","Def":"俗歟　アシタ(LLH\")　シリキレワラクツ(ク-ウ)","KRID_sn":"S26384","KRID":"K07087630"},{"KR2ID":"K0708764","KR_Tenri_p":"Tb381641","KR_vol_name":"法下","KR_radical":"尸","KR_vol":"v7","KR_radical_num":71,"Entry":"ー（屐）","Def":"クツヽケノアシタ(LLLL@LLL\")","KRID_sn":"S26385","KRID":"K07087641"},{"KR2ID":"K0708764","KR_Tenri_p":"Tb381641","KR_vol_name":"法下","KR_radical":"尸","KR_vol":"v7","KR_radical_num":71,"Entry":"⿸尸徒","Def":"クツヽケノアシタ(LLLL@LLL\")","KRID_sn":"S26386","KRID":"K07087642"},{"KR2ID":"K0708771","KR_Tenri_p":"Tb381711","KR_vol_name":"法下","KR_radical":"尸","KR_vol":"v7","KR_radical_num":71,"Entry":"⿸尸技","Def":"同","KRID_sn":"S26387","KRID":"K07087711"},{"KR2ID":"K0708771","KR_Tenri_p":"Tb381711","KR_vol_name":"法下","KR_radical":"尸","KR_vol":"v7","KR_radical_num":71,"Entry":"子","Def":"同","KRID_sn":"S26388","KRID":"K07087712"},{"KR2ID":"K0708772","KR_Tenri_p":"Tb381720","KR_vol_name":"法下","KR_radical":"尸","KR_vol":"v7","KR_radical_num":71,"Entry":"屑","Def":"「《玉》云先結切」　音薛　クタク-ケ(LL\"@-L)　スナホニ(LH@@)　スクナシ(LL@@)　イタハル　クツ(LH\")　物ノカス　勞也　願也　不安也　ウヤマウ(HH@@)　イサキヨシ(HH@@@)　コトヽヽクニ　呉節","KRID_sn":"S26389","KRID":"K07087720"},{"KR2ID":"K0708781","KR_Tenri_p":"Tb381811","KR_vol_name":"法下","KR_radical":"尸","KR_vol":"v7","KR_radical_num":71,"Entry":"金","Def":"（無）","KRID_sn":"S26390","KRID":"K07087811"},{"KR2ID":"K0708781","KR_Tenri_p":"Tb381811","KR_vol_name":"法下","KR_radical":"尸","KR_vol":"v7","KR_radical_num":71,"Entry":"ー（屑）","Def":"（無）","KRID_sn":"S26391","KRID":"K07087812"},{"KR2ID":"K0708782","KR_Tenri_p":"Tb381821","KR_vol_name":"法下","KR_radical":"尸","KR_vol":"v7","KR_radical_num":71,"Entry":"銀","Def":"（無）","KRID_sn":"S26392","KRID":"K07087821"},{"KR2ID":"K0708782","KR_Tenri_p":"Tb381821","KR_vol_name":"法下","KR_radical":"尸","KR_vol":"v7","KR_radical_num":71,"Entry":"ー（屑）","Def":"（無）","KRID_sn":"S26393","KRID":"K07087822"},{"KR2ID":"K0708783","KR_Tenri_p":"Tb381830","KR_vol_name":"法下","KR_radical":"尸","KR_vol":"v7","KR_radical_num":71,"Entry":"㞕","Def":"先結反","KRID_sn":"S26394","KRID":"K07087830"},{"KR2ID":"K0708784","KR_Tenri_p":"Tb381840","KR_vol_name":"法下","KR_radical":"尸","KR_vol":"v7","KR_radical_num":71,"Entry":"尾","Def":"亡匪反　和名ヲ(L)　ツルフ(LL@)　ヲハル　ヤウヤク　和ヒ(L)　又在下","KRID_sn":"S26395","KRID":"K07087840"},{"KR2ID":"K07088121","KR_Tenri_p":"Tb382121","KR_vol_name":"法下","KR_radical":"尸","KR_vol":"v7","KR_radical_num":71,"Entry":"⿸尸⿳八八乚","Def":"正","KRID_sn":"S26396","KRID":"K07088121"},{"KR2ID":"K07088122","KR_Tenri_p":"Tb382122","KR_vol_name":"法下","KR_radical":"尸","KR_vol":"v7","KR_radical_num":71,"Entry":"㞑","Def":"今","KRID_sn":"S26397","KRID":"K07088122"},{"KR2ID":"K07088123","KR_Tenri_p":"Tb382123","KR_vol_name":"法下","KR_radical":"尸","KR_vol":"v7","KR_radical_num":71,"Entry":"⿸尸⿲⿱人人乚⿱人人","Def":"俗","KRID_sn":"S26398","KRID":"K07088123"},{"KR2ID":"K0708814","KR_Tenri_p":"Tb382140","KR_vol_name":"法下","KR_radical":"尸","KR_vol":"v7","KR_radical_num":71,"Entry":"𨾈","Def":"俗雇字　音故　ヤトフ","KRID_sn":"S26399","KRID":"K07088140"},{"KR2ID":"K0708821","KR_Tenri_p":"Tb382210","KR_vol_name":"法下","KR_radical":"尸","KR_vol":"v7","KR_radical_num":71,"Entry":"眉","Def":"明悲反　睂〈正〉　𣮮〈俗〉　ヨシ","KRID_sn":"S26400","KRID":"K07088210"},{"KR2ID":"K0708822","KR_Tenri_p":"Tb382220","KR_vol_name":"法下","KR_radical":"尸","KR_vol":"v7","KR_radical_num":71,"Entry":"⿸尸目","Def":"俗歟","KRID_sn":"S26401","KRID":"K07088220"},{"KR2ID":"K0708823","KR_Tenri_p":"Tb382230","KR_vol_name":"法下","KR_radical":"尸","KR_vol":"v7","KR_radical_num":71,"Entry":"㞒","Def":"許器反　卧皃","KRID_sn":"S26402","KRID":"K07088230"},{"KR2ID":"K0708824","KR_Tenri_p":"Tb382240","KR_vol_name":"法下","KR_radical":"尸","KR_vol":"v7","KR_radical_num":71,"Entry":"届","Def":"音介(R)　イタル(HH@)　ヨル　キハム-マル(LL@-HL)　トツク　フクリ","KRID_sn":"S26403","KRID":"K07088240"},{"KR2ID":"K0708831","KR_Tenri_p":"Tb382310","KR_vol_name":"法下","KR_radical":"尸","KR_vol":"v7","KR_radical_num":71,"Entry":"𡱔","Def":"結二反　又駈馳　又尻","KRID_sn":"S26404","KRID":"K07088310"},{"KR2ID":"K07088321","KR_Tenri_p":"Tb382321","KR_vol_name":"法下","KR_radical":"尸","KR_vol":"v7","KR_radical_num":71,"Entry":"㞓","Def":"正","KRID_sn":"S26405","KRID":"K07088321"},{"KR2ID":"K07088322","KR_Tenri_p":"Tb382322","KR_vol_name":"法下","KR_radical":"尸","KR_vol":"v7","KR_radical_num":71,"Entry":"⿸尸棄","Def":"俗","KRID_sn":"S26406","KRID":"K07088322"},{"KR2ID":"K07088323","KR_Tenri_p":"Tb382323","KR_vol_name":"法下","KR_radical":"尸","KR_vol":"v7","KR_radical_num":71,"Entry":"㞛","Def":"几音　絢皃","KRID_sn":"S26407","KRID":"K07088323"},{"KR2ID":"K0708834","KR_Tenri_p":"Tb382340","KR_vol_name":"法下","KR_radical":"尸","KR_vol":"v7","KR_radical_num":71,"Entry":"⿸尸音","Def":"俗蔭字","KRID_sn":"S26408","KRID":"K07088340"},{"KR2ID":"K0708841","KR_Tenri_p":"Tb382411","KR_vol_name":"法下","KR_radical":"尸","KR_vol":"v7","KR_radical_num":71,"Entry":"⿸尸⿳丷人出","Def":"巨勿反　巨月反　无尾","KRID_sn":"S26409","KRID":"K07088411"},{"KR2ID":"K0708841","KR_Tenri_p":"Tb382411","KR_vol_name":"法下","KR_radical":"尸","KR_vol":"v7","KR_radical_num":71,"Entry":"𡲬","Def":"巨勿反　巨月反　无尾","KRID_sn":"S26410","KRID":"K07088412"},{"KR2ID":"K0708842","KR_Tenri_p":"Tb382420","KR_vol_name":"法下","KR_radical":"尸","KR_vol":"v7","KR_radical_num":71,"Entry":"⿸尸⿱⿲仌｜仌出","Def":"俗","KRID_sn":"S26411","KRID":"K07088420"},{"KR2ID":"K0708843","KR_Tenri_p":"Tb382430","KR_vol_name":"法下","KR_radical":"尸","KR_vol":"v7","KR_radical_num":71,"Entry":"屈","Def":"蓲勿(S\")反　カヽム-マル(HH\"L-HL)　ヲサム(LLH)　マケテ(@L\"@)　クシク(HH\"@)　ウヤマフ　イタス　ツキヌ(HLH)　和音クツ(LL)","KRID_sn":"S26412","KRID":"K07088430"},{"KR2ID":"K0708851","KR_Tenri_p":"Tb382511","KR_vol_name":"法下","KR_radical":"尸","KR_vol":"v7","KR_radical_num":71,"Entry":"⿸尸⿰扌⿱一用","Def":"音㴜　中一又音扁","KRID_sn":"S26413","KRID":"K07088511"},{"KR2ID":"K0708851","KR_Tenri_p":"Tb382511","KR_vol_name":"法下","KR_radical":"尸","KR_vol":"v7","KR_radical_num":71,"Entry":"⿸尸⿰丬⿸戸⿱一冊","Def":"音㴜　中一又音扁","KRID_sn":"S26414","KRID":"K07088512"},{"KR2ID":"K0708851","KR_Tenri_p":"Tb382511","KR_vol_name":"法下","KR_radical":"尸","KR_vol":"v7","KR_radical_num":71,"Entry":"⿸尸⿰丬⿱𠂉巾","Def":"音㴜　中一又音扁","KRID_sn":"S26415","KRID":"K07088513"},{"KR2ID":"K0708853","KR_Tenri_p":"Tb382530","KR_vol_name":"法下","KR_radical":"尸","KR_vol":"v7","KR_radical_num":71,"Entry":"𡱅","Def":"俗㧁字　口予反","KRID_sn":"S26416","KRID":"K07088530"},{"KR2ID":"K0708854","KR_Tenri_p":"Tb382540","KR_vol_name":"法下","KR_radical":"尸","KR_vol":"v7","KR_radical_num":71,"Entry":"𡱳","Def":"索何反","KRID_sn":"S26417","KRID":"K07088540"},{"KR2ID":"K0708861","KR_Tenri_p":"Tb382610","KR_vol_name":"法下","KR_radical":"尸","KR_vol":"v7","KR_radical_num":71,"Entry":"㞌","Def":"俗孕字","KRID_sn":"S26418","KRID":"K07088610"},{"KR2ID":"K0708862","KR_Tenri_p":"Tb382620","KR_vol_name":"法下","KR_radical":"尸","KR_vol":"v7","KR_radical_num":71,"Entry":"孱","Def":"士山反　アラハニ　アキラカニ　又上声　ミル　ヒトシカラス　ウチカヘス　又音煎(L)　仁謹皃　又惡","KRID_sn":"S26419","KRID":"K07088620"},{"KR2ID":"K0708864","KR_Tenri_p":"Tb382640","KR_vol_name":"法下","KR_radical":"尸","KR_vol":"v7","KR_radical_num":71,"Entry":"⿸尸畏","Def":"音哀　養","KRID_sn":"S26420","KRID":"K07088640"},{"KR2ID":"K0708871","KR_Tenri_p":"Tb382710","KR_vol_name":"法下","KR_radical":"尸","KR_vol":"v7","KR_radical_num":71,"Entry":"⿸尸畏","Def":"俗裏字　音里","KRID_sn":"S26421","KRID":"K07088710"},{"KR2ID":"K0708872","KR_Tenri_p":"Tb382720","KR_vol_name":"法下","KR_radical":"尸","KR_vol":"v7","KR_radical_num":71,"Entry":"⿸尸票","Def":"音漂","KRID_sn":"S26422","KRID":"K07088720"},{"KR2ID":"K0708873","KR_Tenri_p":"Tb382731","KR_vol_name":"法下","KR_radical":"尸","KR_vol":"v7","KR_radical_num":71,"Entry":"𡱰","Def":"俗豚字　丁竅　音禿「歟」　シリタムラ(LLLHL)　音笠　同上歟","KRID_sn":"S26423","KRID":"K07088731"},{"KR2ID":"K0708873","KR_Tenri_p":"Tb382731","KR_vol_name":"法下","KR_radical":"尸","KR_vol":"v7","KR_radical_num":71,"Entry":"⿸尸厶","Def":"俗豚字　丁竅　音禿「歟」　シリタムラ(LLLHL)　音笠　同上歟","KRID_sn":"S26424","KRID":"K07088732"},{"KR2ID":"K0708873","KR_Tenri_p":"Tb382731","KR_vol_name":"法下","KR_radical":"尸","KR_vol":"v7","KR_radical_num":71,"Entry":"𡰪","Def":"俗豚字　丁竅　音禿「歟」　シリタムラ(LLLHL)　音笠　同上歟","KRID_sn":"S26425","KRID":"K07088733"},{"KR2ID":"K0708881","KR_Tenri_p":"Tb382810","KR_vol_name":"法下","KR_radical":"尸","KR_vol":"v7","KR_radical_num":71,"Entry":"𡲎","Def":"音箆　未詳　應碑字　父支反","KRID_sn":"S26426","KRID":"K07088810"},{"KR2ID":"K0708882","KR_Tenri_p":"Tb382820","KR_vol_name":"法下","KR_radical":"尸","KR_vol":"v7","KR_radical_num":71,"Entry":"𡲐","Def":"俗乳字","KRID_sn":"S26427","KRID":"K07088820"},{"KR2ID":"K0708883","KR_Tenri_p":"Tb382830","KR_vol_name":"法下","KR_radical":"尸","KR_vol":"v7","KR_radical_num":71,"Entry":"𡰼","Def":"フス","KRID_sn":"S26428","KRID":"K07088830"},{"KR2ID":"K0708884","KR_Tenri_p":"Tb382841","KR_vol_name":"法下","KR_radical":"尸","KR_vol":"v7","KR_radical_num":71,"Entry":"⿸尸⿰彳⿱甘⿵冂𢆉","Def":"音脚　ワラクツ(LLL\"L、ク-ウ(L))　ワラツ(LLH\")","KRID_sn":"S26429","KRID":"K07088841"},{"KR2ID":"K0708884","KR_Tenri_p":"Tb382841","KR_vol_name":"法下","KR_radical":"尸","KR_vol":"v7","KR_radical_num":71,"Entry":"屩","Def":"音脚　ワラクツ(LLL\"L、ク-ウ(L))　ワラツ(LLH\")","KRID_sn":"S26430","KRID":"K07088842"},{"KR2ID":"K07089111","KR_Tenri_p":"Tb383111","KR_vol_name":"法下","KR_radical":"尸","KR_vol":"v7","KR_radical_num":71,"Entry":"屩","Def":"正","KRID_sn":"S26431","KRID":"K07089111"},{"KR2ID":"K07089112","KR_Tenri_p":"Tb383112","KR_vol_name":"法下","KR_radical":"尸","KR_vol":"v7","KR_radical_num":71,"Entry":"⿸尸⿰丬⿱有冋","Def":"俗","KRID_sn":"S26432","KRID":"K07089112"},{"KR2ID":"K0708912","KR_Tenri_p":"Tb383121","KR_vol_name":"法下","KR_radical":"尸","KR_vol":"v7","KR_radical_num":71,"Entry":"⿸尸⿰丬𠳮","Def":"ワラウツノチヲ(@@@@@LL)","KRID_sn":"S26433","KRID":"K07089121"},{"KR2ID":"K0708912","KR_Tenri_p":"Tb383121","KR_vol_name":"法下","KR_radical":"尸","KR_vol":"v7","KR_radical_num":71,"Entry":"耳","Def":"ワラウツノチヲ(@@@@@LL)","KRID_sn":"S26434","KRID":"K07089122"},{"KR2ID":"K0708913","KR_Tenri_p":"Tb383131","KR_vol_name":"法下","KR_radical":"尸","KR_vol":"v7","KR_radical_num":71,"Entry":"ー（屩）","Def":"（無）","KRID_sn":"S26435","KRID":"K07089131"},{"KR2ID":"K0708913","KR_Tenri_p":"Tb383131","KR_vol_name":"法下","KR_radical":"尸","KR_vol":"v7","KR_radical_num":71,"Entry":"靪","Def":"（無）","KRID_sn":"S26436","KRID":"K07089132"},{"KR2ID":"K0708914","KR_Tenri_p":"Tb383140","KR_vol_name":"法下","KR_radical":"尸","KR_vol":"v7","KR_radical_num":71,"Entry":"屠","Def":"音徒(L)　ホフル(LH\"L)　コロス(HH@)　ヤム(LH)　⿸尸緒〈俗〉　破也　裂也　又音除(L)　和ト(L)","KRID_sn":"S26437","KRID":"K07089140"},{"KR2ID":"K0708922","KR_Tenri_p":"Tb383220","KR_vol_name":"法下","KR_radical":"尸","KR_vol":"v7","KR_radical_num":71,"Entry":"層","Def":"昨徒反　一音曽(L)　シナ　カサヌ(HHL)　シキル　塔ノコシ(@LHL)　コシ(HL)　タカシ","KRID_sn":"S26438","KRID":"K07089220"},{"KR2ID":"K0708924","KR_Tenri_p":"Tb383241","KR_vol_name":"法下","KR_radical":"尸","KR_vol":"v7","KR_radical_num":71,"Entry":"層","Def":"トカサネカマへタリ","KRID_sn":"S26439","KRID":"K07089241"},{"KR2ID":"K0708924","KR_Tenri_p":"Tb383241","KR_vol_name":"法下","KR_radical":"尸","KR_vol":"v7","KR_radical_num":71,"Entry":"搆","Def":"トカサネカマへタリ","KRID_sn":"S26440","KRID":"K07089242"},{"KR2ID":"K0708931","KR_Tenri_p":"Tb383310","KR_vol_name":"法下","KR_radical":"尸","KR_vol":"v7","KR_radical_num":71,"Entry":"屜","Def":"他計反　⿰革⿱鹿日ー","KRID_sn":"S26441","KRID":"K07089310"},{"KR2ID":"K0708932","KR_Tenri_p":"Tb383320","KR_vol_name":"法下","KR_radical":"尸","KR_vol":"v7","KR_radical_num":71,"Entry":"⿸尸⿰彳也","Def":"俗","KRID_sn":"S26442","KRID":"K07089320"},{"KR2ID":"K0708933","KR_Tenri_p":"Tb383331","KR_vol_name":"法下","KR_radical":"尸","KR_vol":"v7","KR_radical_num":71,"Entry":"⿸尸⿰丬世","Def":"ナメ(HH)　鞍馬","KRID_sn":"S26443","KRID":"K07089331"},{"KR2ID":"K0708933","KR_Tenri_p":"Tb383331","KR_vol_name":"法下","KR_radical":"尸","KR_vol":"v7","KR_radical_num":71,"Entry":"脊","Def":"ナメ(HH)　鞍馬","KRID_sn":"S26444","KRID":"K07089332"},{"KR2ID":"K0708934","KR_Tenri_p":"Tb383340","KR_vol_name":"法下","KR_radical":"尸","KR_vol":"v7","KR_radical_num":71,"Entry":"屉","Def":"メクル　クツノシキ","KRID_sn":"S26445","KRID":"K07089340"},{"KR2ID":"K0708941","KR_Tenri_p":"Tb383410","KR_vol_name":"法下","KR_radical":"尸","KR_vol":"v7","KR_radical_num":71,"Entry":"𡲾","Def":"大和反　有𩒐履","KRID_sn":"S26446","KRID":"K07089410"},{"KR2ID":"K07089421","KR_Tenri_p":"Tb383421","KR_vol_name":"法下","KR_radical":"尸","KR_vol":"v7","KR_radical_num":71,"Entry":"⿸尸⿰彳⿱禾反","Def":"二正","KRID_sn":"S26447","KRID":"K07089421"},{"KR2ID":"K07089422","KR_Tenri_p":"Tb383422","KR_vol_name":"法下","KR_radical":"尸","KR_vol":"v7","KR_radical_num":71,"Entry":"㞜","Def":"俗","KRID_sn":"S26448","KRID":"K07089422"},{"KR2ID":"K0708943","KR_Tenri_p":"Tb383430","KR_vol_name":"法下","KR_radical":"尸","KR_vol":"v7","KR_radical_num":71,"Entry":"居","Def":"舉魚反　ヰル　ヲリ(HL)　オク(HL)　イク(LH)〈生〉　スフ(HL)　〈安居俗〉　ヲリトコロ(HH@@@)　又音基　語助　和コ","KRID_sn":"S26449","KRID":"K07089430"},{"KR2ID":"K07089521","KR_Tenri_p":"Tb383521","KR_vol_name":"法下","KR_radical":"尸","KR_vol":"v7","KR_radical_num":71,"Entry":"凥","Def":"正","KRID_sn":"S26450","KRID":"K07089521"},{"KR2ID":"K07089522","KR_Tenri_p":"Tb383522","KR_vol_name":"法下","KR_radical":"尸","KR_vol":"v7","KR_radical_num":71,"Entry":"㞐","Def":"古","KRID_sn":"S26451","KRID":"K07089522"},{"KR2ID":"K0708953","KR_Tenri_p":"Tb383531","KR_vol_name":"法下","KR_radical":"尸","KR_vol":"v7","KR_radical_num":71,"Entry":"送","Def":"◉送「リ」往「シンタルヲ」事「フ」居「イケルニ」","KRID_sn":"S26452","KRID":"K07089531"},{"KR2ID":"K0708953","KR_Tenri_p":"Tb383531","KR_vol_name":"法下","KR_radical":"尸","KR_vol":"v7","KR_radical_num":71,"Entry":"徃","Def":"◉送「リ」往「シンタルヲ」事「フ」居「イケルニ」","KRID_sn":"S26453","KRID":"K07089532"},{"KR2ID":"K0708953","KR_Tenri_p":"Tb383531","KR_vol_name":"法下","KR_radical":"尸","KR_vol":"v7","KR_radical_num":71,"Entry":"事","Def":"◉送「リ」往「シンタルヲ」事「フ」居「イケルニ」","KRID_sn":"S26454","KRID":"K07089533"},{"KR2ID":"K0708953","KR_Tenri_p":"Tb383531","KR_vol_name":"法下","KR_radical":"尸","KR_vol":"v7","KR_radical_num":71,"Entry":"居","Def":"◉送「リ」往「シンタルヲ」事「フ」居「イケルニ」","KRID_sn":"S26455","KRID":"K07089534"},{"KR2ID":"K0708954","KR_Tenri_p":"Tb383540","KR_vol_name":"法下","KR_radical":"尸","KR_vol":"v7","KR_radical_num":71,"Entry":"屁","Def":"或䊧〈正〉　匹鼻反　ヘヒル　ヘ(L)","KRID_sn":"S26456","KRID":"K07089540"},{"KR2ID":"K0708961","KR_Tenri_p":"Tb383611","KR_vol_name":"法下","KR_radical":"尸","KR_vol":"v7","KR_radical_num":71,"Entry":"放","Def":"ヘヒル(LLH)","KRID_sn":"S26457","KRID":"K07089611"},{"KR2ID":"K0708961","KR_Tenri_p":"Tb383611","KR_vol_name":"法下","KR_radical":"尸","KR_vol":"v7","KR_radical_num":71,"Entry":"ー（屁）","Def":"ヘヒル(LLH)","KRID_sn":"S26458","KRID":"K07089612"},{"KR2ID":"K0708962","KR_Tenri_p":"Tb383620","KR_vol_name":"法下","KR_radical":"尸","KR_vol":"v7","KR_radical_num":71,"Entry":"𡱂","Def":"正　大門反　尻　ー臀〈今〉　⿱殿骨〈或〉　臋","KRID_sn":"S26459","KRID":"K07089620"},{"KR2ID":"K0708963","KR_Tenri_p":"Tb383630","KR_vol_name":"法下","KR_radical":"尸","KR_vol":"v7","KR_radical_num":71,"Entry":"尻","Def":"苦高反　シリ(LL)　ヰサラヒ　スフ　和高","KRID_sn":"S26460","KRID":"K07089630"},{"KR2ID":"K0708964","KR_Tenri_p":"Tb383640","KR_vol_name":"法下","KR_radical":"尸","KR_vol":"v7","KR_radical_num":71,"Entry":"㞍","Def":"俗","KRID_sn":"S26461","KRID":"K07089640"},{"KR2ID":"K0708971","KR_Tenri_p":"Tb383710","KR_vol_name":"法下","KR_radical":"尸","KR_vol":"v7","KR_radical_num":71,"Entry":"屎","Def":"許伊(L)反　呻吟也　又式規反　又音矢　クソヤ　和シ","KRID_sn":"S26462","KRID":"K07089710"},{"KR2ID":"K0708973","KR_Tenri_p":"Tb383731","KR_vol_name":"法下","KR_radical":"尸","KR_vol":"v7","KR_radical_num":71,"Entry":"⿸尸⿱⿲二｜二米","Def":"二正","KRID_sn":"S26463","KRID":"K07089731"},{"KR2ID":"K0708973","KR_Tenri_p":"Tb383731","KR_vol_name":"法下","KR_radical":"尸","KR_vol":"v7","KR_radical_num":71,"Entry":"𡱁","Def":"二正","KRID_sn":"S26464","KRID":"K07089732"},{"KR2ID":"K0708974","KR_Tenri_p":"Tb383741","KR_vol_name":"法下","KR_radical":"尸","KR_vol":"v7","KR_radical_num":71,"Entry":"𡲘","Def":"⿰⿸尸⿱巛天尾⿰⿸尸⿱厶天⿱己大〈俗〉𦳊《説文》","KRID_sn":"S26465","KRID":"K07089741"},{"KR2ID":"K0708974","KR_Tenri_p":"Tb383741","KR_vol_name":"法下","KR_radical":"尸","KR_vol":"v7","KR_radical_num":71,"Entry":"⿸尸⿱⿰厶厶大","Def":"⿰⿸尸⿱巛天尾⿰⿸尸⿱厶天⿱己大〈俗〉𦳊《説文》","KRID_sn":"S26466","KRID":"K07089742"},{"KR2ID":"K0708974","KR_Tenri_p":"Tb383741","KR_vol_name":"法下","KR_radical":"尸","KR_vol":"v7","KR_radical_num":71,"Entry":"𡲑","Def":"⿰⿸尸⿱巛天尾⿰⿸尸⿱厶天⿱己大〈俗〉𦳊《説文》","KRID_sn":"S26467","KRID":"K07089743"},{"KR2ID":"K0708974","KR_Tenri_p":"Tb383741","KR_vol_name":"法下","KR_radical":"尸","KR_vol":"v7","KR_radical_num":71,"Entry":"⿸尸⿱巛米","Def":"⿰⿸尸⿱巛天尾⿰⿸尸⿱厶天⿱己大〈俗〉𦳊《説文》","KRID_sn":"S26468","KRID":"K07089744"},{"KR2ID":"K0708974","KR_Tenri_p":"Tb383741","KR_vol_name":"法下","KR_radical":"尸","KR_vol":"v7","KR_radical_num":71,"Entry":"⿸尸⿱巛示","Def":"⿰⿸尸⿱巛天尾⿰⿸尸⿱厶天⿱己大〈俗〉𦳊《説文》","KRID_sn":"S26469","KRID":"K07089745"},{"KR2ID":"K0708974","KR_Tenri_p":"Tb383741","KR_vol_name":"法下","KR_radical":"尸","KR_vol":"v7","KR_radical_num":71,"Entry":"⿸尸⿱⿰三三大","Def":"⿰⿸尸⿱巛天尾⿰⿸尸⿱厶天⿱己大〈俗〉𦳊《説文》","KRID_sn":"S26470","KRID":"K07089746"},{"KR2ID":"K0708974","KR_Tenri_p":"Tb383741","KR_vol_name":"法下","KR_radical":"尸","KR_vol":"v7","KR_radical_num":71,"Entry":"⿸尸失","Def":"⿰⿸尸⿱巛天尾⿰⿸尸⿱厶天⿱己大〈俗〉𦳊《説文》","KRID_sn":"S26471","KRID":"K07089747"},{"KR2ID":"K0708974","KR_Tenri_p":"Tb383741","KR_vol_name":"法下","KR_radical":"尸","KR_vol":"v7","KR_radical_num":71,"Entry":"⿸尸⿱公矢","Def":"⿰⿸尸⿱巛天尾⿰⿸尸⿱厶天⿱己大〈俗〉𦳊《説文》","KRID_sn":"S26472","KRID":"K07089748"},{"KR2ID":"K0708983","KR_Tenri_p":"Tb383831","KR_vol_name":"法下","KR_radical":"尸","KR_vol":"v7","KR_radical_num":71,"Entry":"天","Def":"クスネ","KRID_sn":"S26473","KRID":"K07089831"},{"KR2ID":"K0708983","KR_Tenri_p":"Tb383831","KR_vol_name":"法下","KR_radical":"尸","KR_vol":"v7","KR_radical_num":71,"Entry":"鼠","Def":"クスネ","KRID_sn":"S26474","KRID":"K07089832"},{"KR2ID":"K0708983","KR_Tenri_p":"Tb383831","KR_vol_name":"法下","KR_radical":"尸","KR_vol":"v7","KR_radical_num":71,"Entry":"矢","Def":"クスネ","KRID_sn":"S26475","KRID":"K07089833"},{"KR2ID":"K0708984","KR_Tenri_p":"Tb383840","KR_vol_name":"法下","KR_radical":"尸","KR_vol":"v7","KR_radical_num":71,"Entry":"尿","Def":"奴弔反　ユハリ(LH\"H)　又音雖(L)「スヰ」　和ネウ(@H)","KRID_sn":"S26476","KRID":"K07089840"},{"KR2ID":"K0709011","KR_Tenri_p":"Tb384111","KR_vol_name":"法下","KR_radical":"尸","KR_vol":"v7","KR_radical_num":71,"Entry":"𡲘","Def":"二正溺〈或〉　𪝟非","KRID_sn":"S26477","KRID":"K07090111"},{"KR2ID":"K0709011","KR_Tenri_p":"Tb384111","KR_vol_name":"法下","KR_radical":"尸","KR_vol":"v7","KR_radical_num":71,"Entry":"⿸尸⿰⿱父二水","Def":"二正溺〈或〉　𪝟非","KRID_sn":"S26478","KRID":"K07090112"},{"KR2ID":"K0709012","KR_Tenri_p":"Tb384121","KR_vol_name":"法下","KR_radical":"尸","KR_vol":"v7","KR_radical_num":71,"Entry":"⿸尸⿱共火","Def":"六俗","KRID_sn":"S26479","KRID":"K07090121"},{"KR2ID":"K0709012","KR_Tenri_p":"Tb384121","KR_vol_name":"法下","KR_radical":"尸","KR_vol":"v7","KR_radical_num":71,"Entry":"⿸尸⿱水肉","Def":"六俗","KRID_sn":"S26480","KRID":"K07090122"},{"KR2ID":"K0709012","KR_Tenri_p":"Tb384121","KR_vol_name":"法下","KR_radical":"尸","KR_vol":"v7","KR_radical_num":71,"Entry":"𡲳","Def":"六俗","KRID_sn":"S26481","KRID":"K07090123"},{"KR2ID":"K0709012","KR_Tenri_p":"Tb384121","KR_vol_name":"法下","KR_radical":"尸","KR_vol":"v7","KR_radical_num":71,"Entry":"⿸尸溺","Def":"六俗","KRID_sn":"S26482","KRID":"K07090124"},{"KR2ID":"K0709012","KR_Tenri_p":"Tb384121","KR_vol_name":"法下","KR_radical":"尸","KR_vol":"v7","KR_radical_num":71,"Entry":"⿸尸⿱火水","Def":"六俗","KRID_sn":"S26483","KRID":"K07090125"},{"KR2ID":"K0709012","KR_Tenri_p":"Tb384121","KR_vol_name":"法下","KR_radical":"尸","KR_vol":"v7","KR_radical_num":71,"Entry":"⿸尸⿰氵毛","Def":"六俗","KRID_sn":"S26484","KRID":"K07090126"},{"KR2ID":"K0709014","KR_Tenri_p":"Tb384141","KR_vol_name":"法下","KR_radical":"尸","KR_vol":"v7","KR_radical_num":71,"Entry":"⿸尸凶","Def":"香及又許恭反　未詳","KRID_sn":"S26485","KRID":"K07090141"},{"KR2ID":"K0709014","KR_Tenri_p":"Tb384141","KR_vol_name":"法下","KR_radical":"尸","KR_vol":"v7","KR_radical_num":71,"Entry":"⿸尸凶","Def":"香及又許恭反　未詳","KRID_sn":"S26486","KRID":"K07090142"},{"KR2ID":"K0709021","KR_Tenri_p":"Tb384210","KR_vol_name":"法下","KR_radical":"尸","KR_vol":"v7","KR_radical_num":71,"Entry":"屣","Def":"所解反　又纚音　ハキ物　クツ　又平去","KRID_sn":"S26487","KRID":"K07090210"},{"KR2ID":"K07090221","KR_Tenri_p":"Tb384221","KR_vol_name":"法下","KR_radical":"尸","KR_vol":"v7","KR_radical_num":71,"Entry":"⿸尸徒","Def":"今","KRID_sn":"S26488","KRID":"K07090221"},{"KR2ID":"K07090222","KR_Tenri_p":"Tb384222","KR_vol_name":"法下","KR_radical":"尸","KR_vol":"v7","KR_radical_num":71,"Entry":"⿸尸徒","Def":"俗","KRID_sn":"S26489","KRID":"K07090222"},{"KR2ID":"K07090222","KR_Tenri_p":"Tb384222","KR_vol_name":"法下","KR_radical":"尸","KR_vol":"v7","KR_radical_num":71,"Entry":"⿸尸⿰丬走","Def":"俗","KRID_sn":"S26490","KRID":"K07090223"},{"KR2ID":"K0709023","KR_Tenri_p":"Tb384230","KR_vol_name":"法下","KR_radical":"尸","KR_vol":"v7","KR_radical_num":71,"Entry":"𡱍","Def":"俗骸字","KRID_sn":"S26491","KRID":"K07090230"},{"KR2ID":"K0709024","KR_Tenri_p":"Tb384240","KR_vol_name":"法下","KR_radical":"尸","KR_vol":"v7","KR_radical_num":71,"Entry":"属","Def":"音燭「シヨク」　ツク(LH)　又音蜀　トモカラ(HHH\"H)　トモ　ツラヌク　ツトフ　ツラナル　アタル　ヲヨフ　アフ　コノコロ　ハシメ　タクヒ　アツム　イマシ　和ソク","KRID_sn":"S26492","KRID":"K07090240"},{"KR2ID":"K07090331","KR_Tenri_p":"Tb384331","KR_vol_name":"法下","KR_radical":"尸","KR_vol":"v7","KR_radical_num":71,"Entry":"屬","Def":"正","KRID_sn":"S26493","KRID":"K07090331"},{"KR2ID":"K07090332","KR_Tenri_p":"Tb384332","KR_vol_name":"法下","KR_radical":"尸","KR_vol":"v7","KR_radical_num":71,"Entry":"⿸尸蜀","Def":"俗","KRID_sn":"S26494","KRID":"K07090332"},{"KR2ID":"K0709034","KR_Tenri_p":"Tb384340","KR_vol_name":"法下","KR_radical":"尸","KR_vol":"v7","KR_radical_num":71,"Entry":"屏","Def":"餅瓶二音　カクル-ス(LHL-L)　ヘタツ　シノフ　ノソク　ハラフ　シリソク　オシフ　ノフ　ヲサム","KRID_sn":"S26495","KRID":"K07090340"},{"KR2ID":"K0709043","KR_Tenri_p":"Tb384431","KR_vol_name":"法下","KR_radical":"尸","KR_vol":"v7","KR_radical_num":71,"Entry":"ー（屏）","Def":"平声","KRID_sn":"S26496","KRID":"K07090431"},{"KR2ID":"K0709043","KR_Tenri_p":"Tb384431","KR_vol_name":"法下","KR_radical":"尸","KR_vol":"v7","KR_radical_num":71,"Entry":"風","Def":"平声","KRID_sn":"S26497","KRID":"K07090432"},{"KR2ID":"K0709044","KR_Tenri_p":"Tb384440","KR_vol_name":"法下","KR_radical":"尸","KR_vol":"v7","KR_radical_num":71,"Entry":"⿸尸綏","Def":"俗綏字　山危反","KRID_sn":"S26498","KRID":"K07090440"},{"KR2ID":"K0709051","KR_Tenri_p":"Tb384510","KR_vol_name":"法下","KR_radical":"尸","KR_vol":"v7","KR_radical_num":71,"Entry":"㞚","Def":"初戢反　ー㞏徒後躡也　又測給反　ー塞薄","KRID_sn":"S26499","KRID":"K07090510"},{"KR2ID":"K0709053","KR_Tenri_p":"Tb384530","KR_vol_name":"法下","KR_radical":"尸","KR_vol":"v7","KR_radical_num":71,"Entry":"㞚","Def":"正","KRID_sn":"S26500","KRID":"K07090530"},{"KR2ID":"K0709054","KR_Tenri_p":"Tb384540","KR_vol_name":"法下","KR_radical":"尸","KR_vol":"v7","KR_radical_num":71,"Entry":"㞏","Def":"芳乏反　丑立反　又歰蟄二音","KRID_sn":"S26501","KRID":"K07090540"},{"KR2ID":"K0709061","KR_Tenri_p":"Tb384610","KR_vol_name":"法下","KR_radical":"尸","KR_vol":"v7","KR_radical_num":71,"Entry":"𡰫","Def":"或耎字　音軟　又女展反","KRID_sn":"S26502","KRID":"K07090610"},{"KR2ID":"K0709062","KR_Tenri_p":"Tb384620","KR_vol_name":"法下","KR_radical":"尸","KR_vol":"v7","KR_radical_num":71,"Entry":"屒","Def":"音臣　伏","KRID_sn":"S26503","KRID":"K07090620"},{"KR2ID":"K0709063","KR_Tenri_p":"Tb384630","KR_vol_name":"法下","KR_radical":"尸","KR_vol":"v7","KR_radical_num":71,"Entry":"屝","Def":"音翡　草履　ハキ物　クツ","KRID_sn":"S26504","KRID":"K07090630"},{"KR2ID":"K0709064","KR_Tenri_p":"Tb384640","KR_vol_name":"法下","KR_radical":"尸","KR_vol":"v7","KR_radical_num":71,"Entry":"𡲣","Def":"古孝反　又降音　差","KRID_sn":"S26505","KRID":"K07090640"},{"KR2ID":"K0709071","KR_Tenri_p":"Tb384711","KR_vol_name":"法下","KR_radical":"尸","KR_vol":"v7","KR_radical_num":71,"Entry":"㕧","Def":"⿰口𡱁三正　火尸反　呻吟","KRID_sn":"S26506","KRID":"K07090711"},{"KR2ID":"K0709071","KR_Tenri_p":"Tb384711","KR_vol_name":"法下","KR_radical":"尸","KR_vol":"v7","KR_radical_num":71,"Entry":"𣢁","Def":"⿰口𡱁三正　火尸反　呻吟","KRID_sn":"S26507","KRID":"K07090712"},{"KR2ID":"K0709072","KR_Tenri_p":"Tb384720","KR_vol_name":"法下","KR_radical":"尸","KR_vol":"v7","KR_radical_num":71,"Entry":"𡱐","Def":"音夷　踞","KRID_sn":"S26508","KRID":"K07090720"},{"KR2ID":"K0709073","KR_Tenri_p":"Tb384730","KR_vol_name":"法下","KR_radical":"尸","KR_vol":"v7","KR_radical_num":71,"Entry":"𡰾","Def":"⿰車見二正　音次　私視","KRID_sn":"S26509","KRID":"K07090730"},{"KR2ID":"K0709074","KR_Tenri_p":"Tb384740","KR_vol_name":"法下","KR_radical":"尸","KR_vol":"v7","KR_radical_num":71,"Entry":"𡳆","Def":"七盧反　𡪽　今覻","KRID_sn":"S26510","KRID":"K07090740"},{"KR2ID":"K0709081","KR_Tenri_p":"Tb384810","KR_vol_name":"法下","KR_radical":"尸","KR_vol":"v7","KR_radical_num":71,"Entry":"𡱼","Def":"課塊二音　臋　ハセ(LL\")　一云マラ","KRID_sn":"S26511","KRID":"K07090810"},{"KR2ID":"K0709082","KR_Tenri_p":"Tb384820","KR_vol_name":"法下","KR_radical":"尸","KR_vol":"v7","KR_radical_num":71,"Entry":"𡱥","Def":"子回反　或朘","KRID_sn":"S26512","KRID":"K07090820"},{"KR2ID":"K0709083","KR_Tenri_p":"Tb384830","KR_vol_name":"法下","KR_radical":"尸","KR_vol":"v7","KR_radical_num":71,"Entry":"⿸尸衣","Def":"依豈反　大屏風　今扆　ヨソヰ","KRID_sn":"S26513","KRID":"K07090830"},{"KR2ID":"K0709084","KR_Tenri_p":"Tb384841","KR_vol_name":"法下","KR_radical":"尸","KR_vol":"v7","KR_radical_num":71,"Entry":"𡱣","Def":"音序　履属","KRID_sn":"S26514","KRID":"K07090841"},{"KR2ID":"K0709084","KR_Tenri_p":"Tb384841","KR_vol_name":"法下","KR_radical":"尸","KR_vol":"v7","KR_radical_num":71,"Entry":"𡳌","Def":"音序　履属","KRID_sn":"S26515","KRID":"K07090842"},{"KR2ID":"K0709111","KR_Tenri_p":"Tb385110","KR_vol_name":"法下","KR_radical":"尸","KR_vol":"v7","KR_radical_num":71,"Entry":"𡳸","Def":"音歴　履下","KRID_sn":"S26516","KRID":"K07091110"},{"KR2ID":"K0709112","KR_Tenri_p":"Tb385121","KR_vol_name":"法下","KR_radical":"尸","KR_vol":"v7","KR_radical_num":71,"Entry":"𡳙","Def":"音燮(S)「セフ」「サフ」　又帖音　或䕈　履中推薦","KRID_sn":"S26517","KRID":"K07091121"},{"KR2ID":"K0709112","KR_Tenri_p":"Tb385121","KR_vol_name":"法下","KR_radical":"尸","KR_vol":"v7","KR_radical_num":71,"Entry":"屧","Def":"音燮(S)「セフ」「サフ」　又帖音　或䕈　履中推薦","KRID_sn":"S26518","KRID":"K07091122"},{"KR2ID":"K0709112","KR_Tenri_p":"Tb385121","KR_vol_name":"法下","KR_radical":"尸","KR_vol":"v7","KR_radical_num":71,"Entry":"屟","Def":"音燮(S)「セフ」「サフ」　又帖音　或䕈　履中推薦","KRID_sn":"S26519","KRID":"K07091123"},{"KR2ID":"K0709114","KR_Tenri_p":"Tb385140","KR_vol_name":"法下","KR_radical":"尸","KR_vol":"v7","KR_radical_num":71,"Entry":"⿸尸羅","Def":"未詳","KRID_sn":"S26520","KRID":"K07091140"},{"KR2ID":"K0709121","KR_Tenri_p":"Tb385210","KR_vol_name":"法下","KR_radical":"尸","KR_vol":"v7","KR_radical_num":71,"Entry":"⿸尸⿰彳夋","Def":"音莎　靴","KRID_sn":"S26521","KRID":"K07091210"},{"KR2ID":"K0709122","KR_Tenri_p":"Tb385220","KR_vol_name":"法下","KR_radical":"尸","KR_vol":"v7","KR_radical_num":71,"Entry":"𡱺","Def":"音劬　履頭飾","KRID_sn":"S26522","KRID":"K07091220"},{"KR2ID":"K0709123","KR_Tenri_p":"Tb385231","KR_vol_name":"法下","KR_radical":"尸","KR_vol":"v7","KR_radical_num":71,"Entry":"⿸尸勾","Def":"カキル　ツホネ　マトヰル　タムロ　セハシ　上俗中通","KRID_sn":"S26523","KRID":"K07091231"},{"KR2ID":"K0709123","KR_Tenri_p":"Tb385231","KR_vol_name":"法下","KR_radical":"尸","KR_vol":"v7","KR_radical_num":71,"Entry":"𡱈","Def":"カキル　ツホネ　マトヰル　タムロ　セハシ　上俗中通","KRID_sn":"S26524","KRID":"K07091232"},{"KR2ID":"K0709131","KR_Tenri_p":"Tb385310","KR_vol_name":"法下","KR_radical":"尸","KR_vol":"v7","KR_radical_num":71,"Entry":"局","Def":"下正","KRID_sn":"S26525","KRID":"K07091310"},{"KR2ID":"K0709132","KR_Tenri_p":"Tb385320","KR_vol_name":"法下","KR_radical":"尸","KR_vol":"v7","KR_radical_num":71,"Entry":"⿸尸⿱壬水","Def":"トリエ","KRID_sn":"S26526","KRID":"K07091320"},{"KR2ID":"K0709133","KR_Tenri_p":"Tb385330","KR_vol_name":"法下","KR_radical":"尸","KR_vol":"v7","KR_radical_num":71,"Entry":"⿸尸⿱口行","Def":"シリタフラ","KRID_sn":"S26527","KRID":"K07091330"},{"KR2ID":"K0709134","KR_Tenri_p":"Tb385340","KR_vol_name":"法下","KR_radical":"尸","KR_vol":"v7","KR_radical_num":71,"Entry":"𡱰","Def":"シリタフラ","KRID_sn":"S26528","KRID":"K07091340"},{"KR2ID":"K0709141","KR_Tenri_p":"Tb385410","KR_vol_name":"法下","KR_radical":"尸","KR_vol":"v7","KR_radical_num":71,"Entry":"⿸尸⿱⿰二二巾","Def":"マフ","KRID_sn":"S26529","KRID":"K07091410"},{"KR2ID":"K0709142","KR_Tenri_p":"Tb385420","KR_vol_name":"法下","KR_radical":"尸","KR_vol":"v7","KR_radical_num":71,"Entry":"杘","Def":"トリエ","KRID_sn":"S26530","KRID":"K07091420"},{"KR2ID":"K0709143","KR_Tenri_p":"Tb385430","KR_vol_name":"法下","KR_radical":"尸","KR_vol":"v7","KR_radical_num":71,"Entry":"𡰷","Def":"ユトリ　戸歟","KRID_sn":"S26531","KRID":"K07091430"},{"KR2ID":"K0709144","KR_Tenri_p":"Tb385440","KR_vol_name":"法下","KR_radical":"尸","KR_vol":"v7","KR_radical_num":71,"Entry":"屍","Def":"音尸(L-R)　カハネ(HH\"H)　フス　イタム　又去　和去","KRID_sn":"S26532","KRID":"K07091440"},{"KR2ID":"K0709151","KR_Tenri_p":"Tb385510","KR_vol_name":"法下","KR_radical":"尸","KR_vol":"v7","KR_radical_num":71,"Entry":"履","Def":"音李　フム　クツ　革也　ハキ物　ウツム　ウア　ヌク　サイハヒ　ヲサム　ワラウツ　オコナフ　和音リ","KRID_sn":"S26533","KRID":"K07091510"},{"KR2ID":"K0709154","KR_Tenri_p":"Tb385541","KR_vol_name":"法下","KR_radical":"尸","KR_vol":"v7","KR_radical_num":71,"Entry":"深","Def":"フカクツ(LLL\"H)","KRID_sn":"S26534","KRID":"K07091541"},{"KR2ID":"K0709154","KR_Tenri_p":"Tb385541","KR_vol_name":"法下","KR_radical":"尸","KR_vol":"v7","KR_radical_num":71,"Entry":"頭","Def":"フカクツ(LLL\"H)","KRID_sn":"S26535","KRID":"K07091542"},{"KR2ID":"K0709154","KR_Tenri_p":"Tb385541","KR_vol_name":"法下","KR_radical":"尸","KR_vol":"v7","KR_radical_num":71,"Entry":"履","Def":"フカクツ(LLL\"H)","KRID_sn":"S26536","KRID":"K07091543"},{"KR2ID":"K0709161","KR_Tenri_p":"Tb385611","KR_vol_name":"法下","KR_radical":"尸","KR_vol":"v7","KR_radical_num":71,"Entry":"單","Def":"タヒ","KRID_sn":"S26537","KRID":"K07091611"},{"KR2ID":"K0709161","KR_Tenri_p":"Tb385611","KR_vol_name":"法下","KR_radical":"尸","KR_vol":"v7","KR_radical_num":71,"Entry":"皮","Def":"タヒ","KRID_sn":"S26538","KRID":"K07091612"},{"KR2ID":"K0709161","KR_Tenri_p":"Tb385611","KR_vol_name":"法下","KR_radical":"尸","KR_vol":"v7","KR_radical_num":71,"Entry":"ー（履）","Def":"タヒ","KRID_sn":"S26539","KRID":"K07091613"},{"KR2ID":"K0709162","KR_Tenri_p":"Tb385621","KR_vol_name":"法下","KR_radical":"尸","KR_vol":"v7","KR_radical_num":71,"Entry":"鼻","Def":"鼻廣是歟","KRID_sn":"S26540","KRID":"K07091621"},{"KR2ID":"K0709162","KR_Tenri_p":"Tb385621","KR_vol_name":"法下","KR_radical":"尸","KR_vol":"v7","KR_radical_num":71,"Entry":"高","Def":"鼻廣是歟","KRID_sn":"S26541","KRID":"K07091622"},{"KR2ID":"K0709162","KR_Tenri_p":"Tb385621","KR_vol_name":"法下","KR_radical":"尸","KR_vol":"v7","KR_radical_num":71,"Entry":"ー（履）","Def":"鼻廣是歟","KRID_sn":"S26542","KRID":"K07091623"},{"KR2ID":"K0709163","KR_Tenri_p":"Tb385631","KR_vol_name":"法下","KR_radical":"尸","KR_vol":"v7","KR_radical_num":71,"Entry":"草","Def":"ワラクツ　俗云サウリ","KRID_sn":"S26543","KRID":"K07091631"},{"KR2ID":"K0709163","KR_Tenri_p":"Tb385631","KR_vol_name":"法下","KR_radical":"尸","KR_vol":"v7","KR_radical_num":71,"Entry":"ー（履）","Def":"ワラクツ　俗云サウリ","KRID_sn":"S26544","KRID":"K07091632"},{"KR2ID":"K0709164","KR_Tenri_p":"Tb385641","KR_vol_name":"法下","KR_radical":"尸","KR_vol":"v7","KR_radical_num":71,"Entry":"踐","Def":"合云フム","KRID_sn":"S26545","KRID":"K07091641"},{"KR2ID":"K0709164","KR_Tenri_p":"Tb385641","KR_vol_name":"法下","KR_radical":"尸","KR_vol":"v7","KR_radical_num":71,"Entry":"ー（履）","Def":"合云フム","KRID_sn":"S26546","KRID":"K07091642"},{"KR2ID":"K0709171","KR_Tenri_p":"Tb385711","KR_vol_name":"法下","KR_radical":"尸","KR_vol":"v7","KR_radical_num":71,"Entry":"蹠","Def":"ワラクツヽクル(LLL\"HLLH)　クツオル(LLHL)","KRID_sn":"S26547","KRID":"K07091711"},{"KR2ID":"K0709171","KR_Tenri_p":"Tb385711","KR_vol_name":"法下","KR_radical":"尸","KR_vol":"v7","KR_radical_num":71,"Entry":"ー（履）","Def":"ワラクツヽクル(LLL\"HLLH)　クツオル(LLHL)","KRID_sn":"S26548","KRID":"K07091712"},{"KR2ID":"K0709172","KR_Tenri_p":"Tb385720","KR_vol_name":"法下","KR_radical":"尸","KR_vol":"v7","KR_radical_num":71,"Entry":"展","Def":"ノフ(LH)　ウヤマフ　ヒラク　トヽノフ　マコト(LH@)　メクル　タマキ　筞也　ツハヒラカニ(LL\"@@@@)　ヒロク(HH@)〈眉〉　和チン(LL)　テム","KRID_sn":"S26549","KRID":"K07091720"},{"KR2ID":"K0709181","KR_Tenri_p":"Tb385811","KR_vol_name":"法下","KR_radical":"尸","KR_vol":"v7","KR_radical_num":71,"Entry":"ー（展）","Def":"マメス(HH@)","KRID_sn":"S26550","KRID":"K07091811"},{"KR2ID":"K0709181","KR_Tenri_p":"Tb385811","KR_vol_name":"法下","KR_radical":"尸","KR_vol":"v7","KR_radical_num":71,"Entry":"季","Def":"マメス(HH@)","KRID_sn":"S26551","KRID":"K07091812"},{"KR2ID":"K0709182","KR_Tenri_p":"Tb385821","KR_vol_name":"法下","KR_radical":"尸","KR_vol":"v7","KR_radical_num":71,"Entry":"⿸𠃜貝","Def":"音呬　オフ　マク　ソムク　タノム　アリ","KRID_sn":"S26552","KRID":"K07091821"},{"KR2ID":"K0709182","KR_Tenri_p":"Tb385821","KR_vol_name":"法下","KR_radical":"尸","KR_vol":"v7","KR_radical_num":71,"Entry":"屓","Def":"音呬　オフ　マク　ソムク　タノム　アリ","KRID_sn":"S26553","KRID":"K07091822"},{"KR2ID":"K0709184","KR_Tenri_p":"Tb385841","KR_vol_name":"法下","KR_radical":"尸","KR_vol":"v7","KR_radical_num":71,"Entry":"屓","Def":"トチカラオコシス(@HHHHHL@)","KRID_sn":"S26554","KRID":"K07091841"},{"KR2ID":"K0709184","KR_Tenri_p":"Tb385841","KR_vol_name":"法下","KR_radical":"尸","KR_vol":"v7","KR_radical_num":71,"Entry":"贔","Def":"トチカラオコシス(@HHHHHL@)","KRID_sn":"S26555","KRID":"K07091842"},{"KR2ID":"K0709211","KR_Tenri_p":"Tb386110","KR_vol_name":"法下","KR_radical":"尸","KR_vol":"v7","KR_radical_num":71,"Entry":"⿸尸報","Def":"ハタハタ　イカラシ","KRID_sn":"S26556","KRID":"K07092110"},{"KR2ID":"K0709212","KR_Tenri_p":"Tb386120","KR_vol_name":"法下","KR_radical":"尸","KR_vol":"v7","KR_radical_num":71,"Entry":"屙","Def":"カハヤ","KRID_sn":"S26557","KRID":"K07092120"},{"KR2ID":"K0709213","KR_Tenri_p":"Tb386130","KR_vol_name":"法下","KR_radical":"尸","KR_vol":"v7","KR_radical_num":71,"Entry":"⿸尸貨","Def":"ノフ","KRID_sn":"S26558","KRID":"K07092130"},{"KR2ID":"K0709214","KR_Tenri_p":"Tb386140","KR_vol_name":"法下","KR_radical":"尸","KR_vol":"v7","KR_radical_num":71,"Entry":"⿸尸萬","Def":"カタシ　ツク","KRID_sn":"S26559","KRID":"K07092140"},{"KR2ID":"K0709221","KR_Tenri_p":"Tb386210","KR_vol_name":"法下","KR_radical":"尸","KR_vol":"v7","KR_radical_num":71,"Entry":"𡲙","Def":"於人反　塞　舊烏見反　非","KRID_sn":"S26560","KRID":"K07092210"},{"KR2ID":"K0709222","KR_Tenri_p":"Tb386220","KR_vol_name":"法下","KR_radical":"尸","KR_vol":"v7","KR_radical_num":71,"Entry":"尺","Def":"昌石反　十寸　タカハカリ(HHH\"HL)","KRID_sn":"S26561","KRID":"K07092220"},{"KR2ID":"K0709223","KR_Tenri_p":"Tb386231","KR_vol_name":"法下","KR_radical":"尸","KR_vol":"v7","KR_radical_num":71,"Entry":"曲","Def":"マカリカネ(HH\"HLL)","KRID_sn":"S26562","KRID":"K07092231"},{"KR2ID":"K0709223","KR_Tenri_p":"Tb386231","KR_vol_name":"法下","KR_radical":"尸","KR_vol":"v7","KR_radical_num":71,"Entry":"ー（尺）","Def":"マカリカネ(HH\"HLL)","KRID_sn":"S26563","KRID":"K07092232"},{"KR2ID":"K0709224","KR_Tenri_p":"Tb386240","KR_vol_name":"法下","KR_radical":"尸","KR_vol":"v7","KR_radical_num":71,"Entry":"屋","Def":"於鹿反　ヤ(R)　居也　形也","KRID_sn":"S26564","KRID":"K07092240"},{"KR2ID":"K0709231","KR_Tenri_p":"Tb386311","KR_vol_name":"法下","KR_radical":"尸","KR_vol":"v7","KR_radical_num":71,"Entry":"ー（屋）","Def":"ヤノへノコケ(LHHHLL)","KRID_sn":"S26565","KRID":"K07092311"},{"KR2ID":"K0709231","KR_Tenri_p":"Tb386311","KR_vol_name":"法下","KR_radical":"尸","KR_vol":"v7","KR_radical_num":71,"Entry":"遊","Def":"ヤノへノコケ(LHHHLL)","KRID_sn":"S26566","KRID":"K07092312"},{"KR2ID":"K0709232","KR_Tenri_p":"Tb386321","KR_vol_name":"法下","KR_radical":"尸","KR_vol":"v7","KR_radical_num":71,"Entry":"孶","Def":"ツルヒ(LLL\")　コオモヒシツルミス(HH@@@@@@@)　上音字","KRID_sn":"S26567","KRID":"K07092321"},{"KR2ID":"K0709232","KR_Tenri_p":"Tb386321","KR_vol_name":"法下","KR_radical":"尸","KR_vol":"v7","KR_radical_num":71,"Entry":"尾","Def":"ツルヒ(LLL\")　コオモヒシツルミス(HH@@@@@@@)　上音字","KRID_sn":"S26568","KRID":"K07092322"},{"KR2ID":"K0709234","KR_Tenri_p":"Tb386341","KR_vol_name":"法下","KR_radical":"尸","KR_vol":"v7","KR_radical_num":71,"Entry":"鹿","Def":"カノハへハラヒ(LLHLHHL)","KRID_sn":"S26569","KRID":"K07092341"},{"KR2ID":"K0709234","KR_Tenri_p":"Tb386341","KR_vol_name":"法下","KR_radical":"尸","KR_vol":"v7","KR_radical_num":71,"Entry":"ー（尾）","Def":"カノハへハラヒ(LLHLHHL)","KRID_sn":"S26570","KRID":"K07092342"},{"KR2ID":"K0709241","KR_Tenri_p":"Tb386411","KR_vol_name":"法下","KR_radical":"尸","KR_vol":"v7","KR_radical_num":71,"Entry":"𦄋","Def":"クツカタ(LLLH\")　屋宅","KRID_sn":"S26571","KRID":"K07092411"},{"KR2ID":"K0709241","KR_Tenri_p":"Tb386411","KR_vol_name":"法下","KR_radical":"尸","KR_vol":"v7","KR_radical_num":71,"Entry":"ー（尾）","Def":"クツカタ(LLLH\")　屋宅","KRID_sn":"S26572","KRID":"K07092412"},{"KR2ID":"K0709242","KR_Tenri_p":"Tb386420","KR_vol_name":"法下","KR_radical":"尸","KR_vol":"v7","KR_radical_num":71,"Entry":"⿸尸⿱心⿰酉殳","Def":"俗殿字","KRID_sn":"S26573","KRID":"K07092420"},{"KR2ID":"K0709243","KR_Tenri_p":"Tb386430","KR_vol_name":"法下","KR_radical":"尸","KR_vol":"v7","KR_radical_num":71,"Entry":"⿸尸⿲二｜二⿱米","Def":"或⿰禾㞑　音味　粥上之薄","KRID_sn":"S26574","KRID":"K07092430"},{"KR2ID":"K0709251","KR_Tenri_p":"Tb386510","KR_vol_name":"法下","KR_radical":"尸","KR_vol":"v7","KR_radical_num":71,"Entry":"戸","Def":"音扈(H)　ト(H)　ヤム　ツカサトル　ヘ(H)　ホノカナリ　和去","KRID_sn":"S26575","KRID":"K07092510"},{"KR2ID":"K0709253","KR_Tenri_p":"Tb386530","KR_vol_name":"法下","KR_radical":"尸","KR_vol":"v7","KR_radical_num":71,"Entry":"户","Def":"今","KRID_sn":"S26576","KRID":"K07092530"},{"KR2ID":"K0709254","KR_Tenri_p":"Tb386540","KR_vol_name":"法下","KR_radical":"尸","KR_vol":"v7","KR_radical_num":71,"Entry":"㦿","Def":"古　又苦减反　窓","KRID_sn":"S26577","KRID":"K07092540"},{"KR2ID":"K0709261","KR_Tenri_p":"Tb386610","KR_vol_name":"法下","KR_radical":"尸","KR_vol":"v7","KR_radical_num":71,"Entry":"雇","Def":"音故(R)「コ」　ヤトフ(LLH)　タヨリ","KRID_sn":"S26578","KRID":"K07092610"},{"KR2ID":"K0709262","KR_Tenri_p":"Tb386620","KR_vol_name":"法下","KR_radical":"尸","KR_vol":"v7","KR_radical_num":71,"Entry":"⿸戶肖","Def":"俗屑字","KRID_sn":"S26579","KRID":"K07092620"},{"KR2ID":"K0709263","KR_Tenri_p":"Tb386630","KR_vol_name":"法下","KR_radical":"尸","KR_vol":"v7","KR_radical_num":71,"Entry":"扃","Def":"音經(L)　トサシ(HHL)　トヒラ　トホソ(HH\"L)","KRID_sn":"S26580","KRID":"K07092630"},{"KR2ID":"K0709264","KR_Tenri_p":"Tb386640","KR_vol_name":"法下","KR_radical":"尸","KR_vol":"v7","KR_radical_num":71,"Entry":"扄","Def":"俗","KRID_sn":"S26581","KRID":"K07092640"},{"KR2ID":"K0709271","KR_Tenri_p":"Tb386710","KR_vol_name":"法下","KR_radical":"尸","KR_vol":"v7","KR_radical_num":71,"Entry":"鳸","Def":"音戸　九ー農桒鳥也　籀𪆚字","KRID_sn":"S26582","KRID":"K07092710"},{"KR2ID":"K0709272","KR_Tenri_p":"Tb386720","KR_vol_name":"法下","KR_radical":"尸","KR_vol":"v7","KR_radical_num":71,"Entry":"𢨶","Def":"俗居字","KRID_sn":"S26583","KRID":"K07092720"},{"KR2ID":"K0709273","KR_Tenri_p":"Tb386730","KR_vol_name":"法下","KR_radical":"尸","KR_vol":"v7","KR_radical_num":71,"Entry":"𢨺","Def":"音遼　穴","KRID_sn":"S26584","KRID":"K07092730"},{"KR2ID":"K0709274","KR_Tenri_p":"Tb386740","KR_vol_name":"法下","KR_radical":"尸","KR_vol":"v7","KR_radical_num":71,"Entry":"扉","Def":"音非　トヒラ(HHL)　トホソ","KRID_sn":"S26585","KRID":"K07092740"},{"KR2ID":"K0709281","KR_Tenri_p":"Tb386810","KR_vol_name":"法下","KR_radical":"尸","KR_vol":"v7","KR_radical_num":71,"Entry":"⿸戶兆","Def":"ソリ(LL)　ホキ","KRID_sn":"S26586","KRID":"K07092810"},{"KR2ID":"K0709282","KR_Tenri_p":"Tb386820","KR_vol_name":"法下","KR_radical":"尸","KR_vol":"v7","KR_radical_num":71,"Entry":"𢩁","Def":"俗𡱈字　ヒトシ　ツカサ","KRID_sn":"S26587","KRID":"K07092820"},{"KR2ID":"K0709283","KR_Tenri_p":"Tb386830","KR_vol_name":"法下","KR_radical":"尸","KR_vol":"v7","KR_radical_num":71,"Entry":"⿸尸巳","Def":"音侯「俊歟」　砌","KRID_sn":"S26588","KRID":"K07092830"},{"KR2ID":"K0709284","KR_Tenri_p":"Tb386840","KR_vol_name":"法下","KR_radical":"尸","KR_vol":"v7","KR_radical_num":71,"Entry":"戺","Def":"◇戺「⿰戸也」　或　ミキリ(LL\"@)","KRID_sn":"S26589","KRID":"K07092840"},{"KR2ID":"K0709311","KR_Tenri_p":"Tb387110","KR_vol_name":"法下","KR_radical":"尸","KR_vol":"v7","KR_radical_num":71,"Entry":"㦾","Def":"ミキリ　アク　コフ","KRID_sn":"S26590","KRID":"K07093110"},{"KR2ID":"K0709312","KR_Tenri_p":"Tb387120","KR_vol_name":"法下","KR_radical":"尸","KR_vol":"v7","KR_radical_num":71,"Entry":"扆","Def":"俗通⿸尸衣字　マト(LH)","KRID_sn":"S26591","KRID":"K07093120"},{"KR2ID":"K0709313","KR_Tenri_p":"Tb387130","KR_vol_name":"法下","KR_radical":"尸","KR_vol":"v7","KR_radical_num":71,"Entry":"㧁","Def":"閣立又苦荅反　開合","KRID_sn":"S26592","KRID":"K07093130"},{"KR2ID":"K0709314","KR_Tenri_p":"Tb387140","KR_vol_name":"法下","KR_radical":"尸","KR_vol":"v7","KR_radical_num":71,"Entry":"扂","Def":"音淡　鍵牡　又云或𠂼　丁泰反　門ー","KRID_sn":"S26593","KRID":"K07093140"},{"KR2ID":"K0709322","KR_Tenri_p":"Tb387220","KR_vol_name":"法下","KR_radical":"尸","KR_vol":"v7","KR_radical_num":71,"Entry":"扊","Def":"正","KRID_sn":"S26594","KRID":"K07093220"},{"KR2ID":"K0709323","KR_Tenri_p":"Tb387230","KR_vol_name":"法下","KR_radical":"尸","KR_vol":"v7","KR_radical_num":71,"Entry":"扅","Def":"音移　鍵牡","KRID_sn":"S26595","KRID":"K07093230"},{"KR2ID":"K0709324","KR_Tenri_p":"Tb387240","KR_vol_name":"法下","KR_radical":"尸","KR_vol":"v7","KR_radical_num":71,"Entry":"𢨹","Def":"或","KRID_sn":"S26596","KRID":"K07093240"},{"KR2ID":"K0709331","KR_Tenri_p":"Tb387310","KR_vol_name":"法下","KR_radical":"尸","KR_vol":"v7","KR_radical_num":71,"Entry":"㧀","Def":"音及　鍵牡","KRID_sn":"S26597","KRID":"K07093310"},{"KR2ID":"K0709332","KR_Tenri_p":"Tb387320","KR_vol_name":"法下","KR_radical":"尸","KR_vol":"v7","KR_radical_num":71,"Entry":"戾","Def":"▲戾「戻」　音麗(R)「レイ」　トシ　スシ　マツ　イタル　タカラ　トヽム-マル(HH\"@-@@)　和ライ(@L)","KRID_sn":"S26598","KRID":"K07093320"},{"KR2ID":"K0709334","KR_Tenri_p":"Tb387340","KR_vol_name":"法下","KR_radical":"尸","KR_vol":"v7","KR_radical_num":71,"Entry":"𭠅","Def":"俗　モトル(LL\"H、ト-チ)　メクル　アカル　サタム　イタル　トル　ミル　キタル　ソムク","KRID_sn":"S26599","KRID":"K07093340"},{"KR2ID":"K0709342","KR_Tenri_p":"Tb387420","KR_vol_name":"法下","KR_radical":"尸","KR_vol":"v7","KR_radical_num":71,"Entry":"启","Def":"ヒラク","KRID_sn":"S26600","KRID":"K07093420"},{"KR2ID":"K0709343","KR_Tenri_p":"Tb387430","KR_vol_name":"法下","KR_radical":"尸","KR_vol":"v7","KR_radical_num":71,"Entry":"扇","Def":"アフキ(LLL)　又𥰢　サハカシ　オトロク(LL\"@@)　シタカフ　タスク(LL@)　トヒラ(HHL)　トシ　アフク(LLH\")","KRID_sn":"S26601","KRID":"K07093430"},{"KR2ID":"K0709351","KR_Tenri_p":"Tb387511","KR_vol_name":"法下","KR_radical":"尸","KR_vol":"v7","KR_radical_num":71,"Entry":"團","Def":"ウチハ","KRID_sn":"S26602","KRID":"K07093511"},{"KR2ID":"K0709351","KR_Tenri_p":"Tb387511","KR_vol_name":"法下","KR_radical":"尸","KR_vol":"v7","KR_radical_num":71,"Entry":"扇","Def":"ウチハ","KRID_sn":"S26603","KRID":"K07093512"},{"KR2ID":"K0709352","KR_Tenri_p":"Tb387520","KR_vol_name":"法下","KR_radical":"尸","KR_vol":"v7","KR_radical_num":71,"Entry":"肩","Def":"柯研反　マトフ　ソムク　ハム","KRID_sn":"S26604","KRID":"K07093520"},{"KR2ID":"K0709353","KR_Tenri_p":"Tb387530","KR_vol_name":"法下","KR_radical":"尸","KR_vol":"v7","KR_radical_num":71,"Entry":"⿸户由","Def":"ツク","KRID_sn":"S26605","KRID":"K07093530"},{"KR2ID":"K0709354","KR_Tenri_p":"Tb387540","KR_vol_name":"法下","KR_radical":"尸","KR_vol":"v7","KR_radical_num":71,"Entry":"扈","Def":"胡戸(H)反　セシム(HHL)　使ー是歟　カフリ　トリコ　緩也　枝也　恣也　ヒラク(LLH)　コヽ　養馬也　勇也　𦂩也","KRID_sn":"S26606","KRID":"K07093540"},{"KR2ID":"K0709363","KR_Tenri_p":"Tb387630","KR_vol_name":"法下","KR_radical":"尸","KR_vol":"v7","KR_radical_num":71,"Entry":"⿸户并","Def":"必野反　ー幛","KRID_sn":"S26607","KRID":"K07093630"},{"KR2ID":"K0709364","KR_Tenri_p":"Tb387640","KR_vol_name":"法下","KR_radical":"尸","KR_vol":"v7","KR_radical_num":71,"Entry":"扁","Def":"音褊　署ー　碥〈或〉","KRID_sn":"S26608","KRID":"K07093640"},{"KR2ID":"K0709371","KR_Tenri_p":"Tb387710","KR_vol_name":"法下","KR_radical":"尸","KR_vol":"v7","KR_radical_num":71,"Entry":"戹","Def":"於隔反　厄字","KRID_sn":"S26609","KRID":"K07093710"},{"KR2ID":"K0709372","KR_Tenri_p":"Tb387720","KR_vol_name":"法下","KR_radical":"尸","KR_vol":"v7","KR_radical_num":71,"Entry":"所","Def":"トコロ(HHH)　和シヨ(LL)","KRID_sn":"S26610","KRID":"K07093720"},{"KR2ID":"K0709373","KR_Tenri_p":"Tb387730","KR_vol_name":"法下","KR_radical":"尸","KR_vol":"v7","KR_radical_num":71,"Entry":"戽","Def":"音故　ユトリ(LLL)","KRID_sn":"S26611","KRID":"K07093730"},{"KR2ID":"K0709374","KR_Tenri_p":"Tb387740","KR_vol_name":"法下","KR_radical":"尸","KR_vol":"v7","KR_radical_num":71,"Entry":"𢩈","Def":"俗屋字","KRID_sn":"S26612","KRID":"K07093740"},{"KR2ID":"K0709381","KR_Tenri_p":"Tb387810","KR_vol_name":"法下","KR_radical":"尸","KR_vol":"v7","KR_radical_num":71,"Entry":"⿸户巾","Def":"タナコヒ","KRID_sn":"S26613","KRID":"K07093810"},{"KR2ID":"K0709382","KR_Tenri_p":"Tb387820","KR_vol_name":"法下","KR_radical":"尸","KR_vol":"v7","KR_radical_num":71,"Entry":"⿸户术","Def":"音述","KRID_sn":"S26614","KRID":"K07093820"},{"KR2ID":"K0709383","KR_Tenri_p":"Tb387830","KR_vol_name":"法下","KR_radical":"尸","KR_vol":"v7","KR_radical_num":71,"Entry":"房","Def":"音防(L)　俗音ハウ(L\"H)　ネヤ(HH)　フサ(LL)　ハナフサ(LL@@)　ツヽム　和ハウ","KRID_sn":"S26615","KRID":"K07093830"},{"KR2ID":"K0709384","KR_Tenri_p":"Tb387840","KR_vol_name":"法下","KR_radical":"尸","KR_vol":"v7","KR_radical_num":71,"Entry":"𢨲","Def":"古","KRID_sn":"S26616","KRID":"K07093840"}]