[{"KR2ID":"K05044511","KR_Tenri_p":"Tb050511","KR_vol_name":"法上","KR_radical":"冫","KR_vol":"v5","KR_radical_num":42,"Entry":"冫","Def":"音氷　凝結也","KRID_sn":"S15763","KRID":"K05044511"},{"KR2ID":"K05044512","KR_Tenri_p":"Tb050512","KR_vol_name":"法上","KR_radical":"冫","KR_vol":"v5","KR_radical_num":42,"Entry":"冫","Def":"正","KRID_sn":"S15764","KRID":"K05044512"},{"KR2ID":"K0504452","KR_Tenri_p":"Tb050521","KR_vol_name":"法上","KR_radical":"冫","KR_vol":"v5","KR_radical_num":42,"Entry":"氷","Def":"上通下正　魚膺反　今為冫字　音在上　和ヒ(L)　一云コホリ(HHH)","KRID_sn":"S15765","KRID":"K05044521"},{"KR2ID":"K0504452","KR_Tenri_p":"Tb050521","KR_vol_name":"法上","KR_radical":"冫","KR_vol":"v5","KR_radical_num":42,"Entry":"冰","Def":"上通下正　魚膺反　今為冫字　音在上　和ヒ(L)　一云コホリ(HHH)","KRID_sn":"S15766","KRID":"K05044522"},{"KR2ID":"K0504454","KR_Tenri_p":"Tb050540","KR_vol_name":"法上","KR_radical":"冫","KR_vol":"v5","KR_radical_num":42,"Entry":"𡿨","Def":"五泫(R)反　水小流皃　ミソ","KRID_sn":"S15767","KRID":"K05044540"},{"KR2ID":"K0504461","KR_Tenri_p":"Tb050611","KR_vol_name":"法上","KR_radical":"冫","KR_vol":"v5","KR_radical_num":42,"Entry":"氷","Def":"イカリノツクル(HHLLL@@)","KRID_sn":"S15768","KRID":"K05044611"},{"KR2ID":"K0504461","KR_Tenri_p":"Tb050611","KR_vol_name":"法上","KR_radical":"冫","KR_vol":"v5","KR_radical_num":42,"Entry":"矝","Def":"イカリノツクル(HHLLL@@)","KRID_sn":"S15769","KRID":"K05044612"},{"KR2ID":"K0504462","KR_Tenri_p":"Tb050620","KR_vol_name":"法上","KR_radical":"冫","KR_vol":"v5","KR_radical_num":42,"Entry":"⿰氵⿱⿱亠吅⿱囬米","Def":"俗","KRID_sn":"S15770","KRID":"K05044620"},{"KR2ID":"K0504463","KR_Tenri_p":"Tb050630","KR_vol_name":"法上","KR_radical":"冫","KR_vol":"v5","KR_radical_num":42,"Entry":"凊","Def":"正清字　七正反","KRID_sn":"S15771","KRID":"K05044630"},{"KR2ID":"K05044641","KR_Tenri_p":"Tb050641","KR_vol_name":"法上","KR_radical":"冫","KR_vol":"v5","KR_radical_num":42,"Entry":"凘","Def":"音斯　コホル","KRID_sn":"S15772","KRID":"K05044641"},{"KR2ID":"K05044642","KR_Tenri_p":"Tb050642","KR_vol_name":"法上","KR_radical":"冫","KR_vol":"v5","KR_radical_num":42,"Entry":"凘","Def":"正","KRID_sn":"S15773","KRID":"K05044642"},{"KR2ID":"K0504471","KR_Tenri_p":"Tb050710","KR_vol_name":"法上","KR_radical":"冫","KR_vol":"v5","KR_radical_num":42,"Entry":"𠗄","Def":"古","KRID_sn":"S15774","KRID":"K05044710"},{"KR2ID":"K0504472","KR_Tenri_p":"Tb050720","KR_vol_name":"法上","KR_radical":"冫","KR_vol":"v5","KR_radical_num":42,"Entry":"凍","Def":"東(L)凍二音　コホリ(H@@、リ-ル)　コル　サムシ　サユ　コヽヒタリ　通凍字　シミナ　コイタリ","KRID_sn":"S15775","KRID":"K05044720"},{"KR2ID":"K0504474","KR_Tenri_p":"Tb050741","KR_vol_name":"法上","KR_radical":"冫","KR_vol":"v5","KR_radical_num":42,"Entry":"ー（凍）","Def":"カンカル","KRID_sn":"S15776","KRID":"K05044741"},{"KR2ID":"K0504474","KR_Tenri_p":"Tb050741","KR_vol_name":"法上","KR_radical":"冫","KR_vol":"v5","KR_radical_num":42,"Entry":"死","Def":"カンカル","KRID_sn":"S15777","KRID":"K05044742"},{"KR2ID":"K0504481","KR_Tenri_p":"Tb050810","KR_vol_name":"法上","KR_radical":"冫","KR_vol":"v5","KR_radical_num":42,"Entry":"凌","Def":"音陵(L)　ハケシ　コホリ","KRID_sn":"S15778","KRID":"K05044810"},{"KR2ID":"K0504482","KR_Tenri_p":"Tb050820","KR_vol_name":"法上","KR_radical":"冫","KR_vol":"v5","KR_radical_num":42,"Entry":"凋","Def":"音琱(L)「テウ」　シホム　カル(HL)　オトロフ(L@H@)　オツ","KRID_sn":"S15779","KRID":"K05044820"},{"KR2ID":"K0504483","KR_Tenri_p":"Tb050830","KR_vol_name":"法上","KR_radical":"冫","KR_vol":"v5","KR_radical_num":42,"Entry":"冶","Def":"音也(H)　ミカク(HH\"@)　トロモス(HH@@)　ミヤヒカリ(L@H\"@@)　ウルハシ(LLLH)　トク(LL\")　キタフ　クル　キル　ウツ(LH)","KRID_sn":"S15780","KRID":"K05044830"},{"KR2ID":"K0504511","KR_Tenri_p":"Tb051110","KR_vol_name":"法上","KR_radical":"冫","KR_vol":"v5","KR_radical_num":42,"Entry":"凚","Def":"琴音　又渠錦反　寒也","KRID_sn":"S15781","KRID":"K05045110"},{"KR2ID":"K0504512","KR_Tenri_p":"Tb051120","KR_vol_name":"法上","KR_radical":"冫","KR_vol":"v5","KR_radical_num":42,"Entry":"𠖷","Def":"或𠖷字　胡頂反　又音熲","KRID_sn":"S15782","KRID":"K05045120"},{"KR2ID":"K0504513","KR_Tenri_p":"Tb051130","KR_vol_name":"法上","KR_radical":"冫","KR_vol":"v5","KR_radical_num":42,"Entry":"凇","Def":"相容反　凍落","KRID_sn":"S15783","KRID":"K05045130"},{"KR2ID":"K0504514","KR_Tenri_p":"Tb051140","KR_vol_name":"法上","KR_radical":"冫","KR_vol":"v5","KR_radical_num":42,"Entry":"凓","Def":"音栗　サムシ","KRID_sn":"S15784","KRID":"K05045140"},{"KR2ID":"K0504521","KR_Tenri_p":"Tb051210","KR_vol_name":"法上","KR_radical":"冫","KR_vol":"v5","KR_radical_num":42,"Entry":"𠘍","Def":"𠘍二正","KRID_sn":"S15785","KRID":"K05045210"},{"KR2ID":"K0504522","KR_Tenri_p":"Tb051220","KR_vol_name":"法上","KR_radical":"冫","KR_vol":"v5","KR_radical_num":42,"Entry":"冽","Def":"音列　寒氣也　⿰氵𠛱正","KRID_sn":"S15786","KRID":"K05045220"},{"KR2ID":"K0504523","KR_Tenri_p":"Tb051230","KR_vol_name":"法上","KR_radical":"冫","KR_vol":"v5","KR_radical_num":42,"Entry":"𠗉","Def":"匣音　ー𠗨","KRID_sn":"S15787","KRID":"K05045230"},{"KR2ID":"K0504524","KR_Tenri_p":"Tb051240","KR_vol_name":"法上","KR_radical":"冫","KR_vol":"v5","KR_radical_num":42,"Entry":"𠗉","Def":"正","KRID_sn":"S15788","KRID":"K05045240"},{"KR2ID":"K0504531","KR_Tenri_p":"Tb051310","KR_vol_name":"法上","KR_radical":"冫","KR_vol":"v5","KR_radical_num":42,"Entry":"𠗨","Def":"直夾反","KRID_sn":"S15789","KRID":"K05045310"},{"KR2ID":"K0504532","KR_Tenri_p":"Tb051321","KR_vol_name":"法上","KR_radical":"冫","KR_vol":"v5","KR_radical_num":42,"Entry":"⿰氵⿱廿木","Def":"二今","KRID_sn":"S15790","KRID":"K05045321"},{"KR2ID":"K0504532","KR_Tenri_p":"Tb051321","KR_vol_name":"法上","KR_radical":"冫","KR_vol":"v5","KR_radical_num":42,"Entry":"㳿","Def":"二今","KRID_sn":"S15791","KRID":"K05045322"},{"KR2ID":"K0504533","KR_Tenri_p":"Tb051330","KR_vol_name":"法上","KR_radical":"冫","KR_vol":"v5","KR_radical_num":42,"Entry":"凗","Def":"徂迴反　ー凒霜雪皃","KRID_sn":"S15792","KRID":"K05045330"},{"KR2ID":"K0504534","KR_Tenri_p":"Tb051340","KR_vol_name":"法上","KR_radical":"冫","KR_vol":"v5","KR_radical_num":42,"Entry":"凒","Def":"五哀反　溰俗非","KRID_sn":"S15793","KRID":"K05045340"},{"KR2ID":"K0504541","KR_Tenri_p":"Tb051410","KR_vol_name":"法上","KR_radical":"冫","KR_vol":"v5","KR_radical_num":42,"Entry":"⿰冫⿱⿰｜三豆","Def":"正","KRID_sn":"S15794","KRID":"K05045410"},{"KR2ID":"K0504542","KR_Tenri_p":"Tb051420","KR_vol_name":"法上","KR_radical":"冫","KR_vol":"v5","KR_radical_num":42,"Entry":"𠗊","Def":"巨井反　寒也　直也","KRID_sn":"S15795","KRID":"K05045420"},{"KR2ID":"K05045431","KR_Tenri_p":"Tb051431","KR_vol_name":"法上","KR_radical":"冫","KR_vol":"v5","KR_radical_num":42,"Entry":"涇","Def":"正","KRID_sn":"S15796","KRID":"K05045431"},{"KR2ID":"K05045432","KR_Tenri_p":"Tb051432","KR_vol_name":"法上","KR_radical":"冫","KR_vol":"v5","KR_radical_num":42,"Entry":"⿰冫⿱平一","Def":"今","KRID_sn":"S15797","KRID":"K05045432"},{"KR2ID":"K0504544","KR_Tenri_p":"Tb051440","KR_vol_name":"法上","KR_radical":"冫","KR_vol":"v5","KR_radical_num":42,"Entry":"凔","Def":"滄或　初亮反　又倉音　寒也","KRID_sn":"S15798","KRID":"K05045440"},{"KR2ID":"K0504551","KR_Tenri_p":"Tb051510","KR_vol_name":"法上","KR_radical":"冫","KR_vol":"v5","KR_radical_num":42,"Entry":"𠗙","Def":"含音　又胡感反　寒","KRID_sn":"S15799","KRID":"K05045510"},{"KR2ID":"K0504552","KR_Tenri_p":"Tb051520","KR_vol_name":"法上","KR_radical":"冫","KR_vol":"v5","KR_radical_num":42,"Entry":"𠗴","Def":"正","KRID_sn":"S15800","KRID":"K05045520"},{"KR2ID":"K0504553","KR_Tenri_p":"Tb051530","KR_vol_name":"法上","KR_radical":"冫","KR_vol":"v5","KR_radical_num":42,"Entry":"⿰冫凾","Def":"俗通","KRID_sn":"S15801","KRID":"K05045530"},{"KR2ID":"K0504554","KR_Tenri_p":"Tb051540","KR_vol_name":"法上","KR_radical":"冫","KR_vol":"v5","KR_radical_num":42,"Entry":"𠗙","Def":"俗","KRID_sn":"S15802","KRID":"K05045540"},{"KR2ID":"K0504561","KR_Tenri_p":"Tb051610","KR_vol_name":"法上","KR_radical":"冫","KR_vol":"v5","KR_radical_num":42,"Entry":"㓖","Def":"必音　寒風","KRID_sn":"S15803","KRID":"K05045610"},{"KR2ID":"K0504562","KR_Tenri_p":"Tb051620","KR_vol_name":"法上","KR_radical":"冫","KR_vol":"v5","KR_radical_num":42,"Entry":"㓖","Def":"正","KRID_sn":"S15804","KRID":"K05045620"},{"KR2ID":"K0504563","KR_Tenri_p":"Tb051630","KR_vol_name":"法上","KR_radical":"冫","KR_vol":"v5","KR_radical_num":42,"Entry":"冹","Def":"弗音　滭也","KRID_sn":"S15805","KRID":"K05045630"},{"KR2ID":"K0504564","KR_Tenri_p":"Tb051640","KR_vol_name":"法上","KR_radical":"冫","KR_vol":"v5","KR_radical_num":42,"Entry":"𠘝","Def":"欶音　寒","KRID_sn":"S15806","KRID":"K05045640"},{"KR2ID":"K0504571","KR_Tenri_p":"Tb051710","KR_vol_name":"法上","KR_radical":"冫","KR_vol":"v5","KR_radical_num":42,"Entry":"𠘝","Def":"俗非","KRID_sn":"S15807","KRID":"K05045710"},{"KR2ID":"K0504572","KR_Tenri_p":"Tb051720","KR_vol_name":"法上","KR_radical":"冫","KR_vol":"v5","KR_radical_num":42,"Entry":"冲","Def":"ヒヽル(HHL)　ムナシ(HH@)","KRID_sn":"S15808","KRID":"K05045720"},{"KR2ID":"K0504573","KR_Tenri_p":"Tb051730","KR_vol_name":"法上","KR_radical":"冫","KR_vol":"v5","KR_radical_num":42,"Entry":"决","Def":"音穴　サクル(LLH)　サタム(LL\"@)　ヿハル　カナラス　タヽス　クシル(LLH)　アマネシ　モトム　キヨシ　ヒラク(LLH)　トル　タノシ　ワカツ　ハマル　ウカツ　クヒル　サル　タケシ　ヤスル　通決字","KRID_sn":"S15809","KRID":"K05045730"},{"KR2ID":"K0504583","KR_Tenri_p":"Tb051830","KR_vol_name":"法上","KR_radical":"冫","KR_vol":"v5","KR_radical_num":42,"Entry":"冬","Def":"𠔙古　都農反　フユ","KRID_sn":"S15810","KRID":"K05045830"},{"KR2ID":"K0504584","KR_Tenri_p":"Tb051841","KR_vol_name":"法上","KR_radical":"冫","KR_vol":"v5","KR_radical_num":42,"Entry":"欵","Def":"ヤマフヽキ(LLL\"LL)　一云ヤマフキ(LLHL)","KRID_sn":"S15811","KRID":"K05045841"},{"KR2ID":"K0504584","KR_Tenri_p":"Tb051841","KR_vol_name":"法上","KR_radical":"冫","KR_vol":"v5","KR_radical_num":42,"Entry":"ー（冬）","Def":"ヤマフヽキ(LLL\"LL)　一云ヤマフキ(LLHL)","KRID_sn":"S15812","KRID":"K05045842"},{"KR2ID":"K0504611","KR_Tenri_p":"Tb052111","KR_vol_name":"法上","KR_radical":"冫","KR_vol":"v5","KR_radical_num":42,"Entry":"忍","Def":"スヒカツラ(HHHH\"L)","KRID_sn":"S15813","KRID":"K05046111"},{"KR2ID":"K0504611","KR_Tenri_p":"Tb052111","KR_vol_name":"法上","KR_radical":"冫","KR_vol":"v5","KR_radical_num":42,"Entry":"ー（冬）","Def":"スヒカツラ(HHHH\"L)","KRID_sn":"S15814","KRID":"K05046112"},{"KR2ID":"K0504612","KR_Tenri_p":"Tb052121","KR_vol_name":"法上","KR_radical":"冫","KR_vol":"v5","KR_radical_num":42,"Entry":"天","Def":"スマロクサ(HH@L\"L)","KRID_sn":"S15815","KRID":"K05046121"},{"KR2ID":"K0504612","KR_Tenri_p":"Tb052121","KR_vol_name":"法上","KR_radical":"冫","KR_vol":"v5","KR_radical_num":42,"Entry":"門","Def":"スマロクサ(HH@L\"L)","KRID_sn":"S15816","KRID":"K05046122"},{"KR2ID":"K0504612","KR_Tenri_p":"Tb052121","KR_vol_name":"法上","KR_radical":"冫","KR_vol":"v5","KR_radical_num":42,"Entry":"ー（冬）","Def":"スマロクサ(HH@L\"L)","KRID_sn":"S15817","KRID":"K05046123"},{"KR2ID":"K0504613","KR_Tenri_p":"Tb052131","KR_vol_name":"法上","KR_radical":"冫","KR_vol":"v5","KR_radical_num":42,"Entry":"麦","Def":"ヤマスケ(LHLL\")","KRID_sn":"S15818","KRID":"K05046131"},{"KR2ID":"K0504613","KR_Tenri_p":"Tb052131","KR_vol_name":"法上","KR_radical":"冫","KR_vol":"v5","KR_radical_num":42,"Entry":"門","Def":"ヤマスケ(LHLL\")","KRID_sn":"S15819","KRID":"K05046132"},{"KR2ID":"K0504613","KR_Tenri_p":"Tb052131","KR_vol_name":"法上","KR_radical":"冫","KR_vol":"v5","KR_radical_num":42,"Entry":"冬","Def":"ヤマスケ(LHLL\")","KRID_sn":"S15820","KRID":"K05046133"},{"KR2ID":"K0504614","KR_Tenri_p":"Tb052141","KR_vol_name":"法上","KR_radical":"冫","KR_vol":"v5","KR_radical_num":42,"Entry":"地","Def":"天門ー　一云ー〻","KRID_sn":"S15821","KRID":"K05046141"},{"KR2ID":"K0504614","KR_Tenri_p":"Tb052141","KR_vol_name":"法上","KR_radical":"冫","KR_vol":"v5","KR_radical_num":42,"Entry":"門","Def":"天門ー　一云ー〻","KRID_sn":"S15822","KRID":"K05046142"},{"KR2ID":"K0504614","KR_Tenri_p":"Tb052141","KR_vol_name":"法上","KR_radical":"冫","KR_vol":"v5","KR_radical_num":42,"Entry":"ー（冬）","Def":"天門ー　一云ー〻","KRID_sn":"S15823","KRID":"K05046143"},{"KR2ID":"K0503381","KR_Tenri_p":"Tb039810","KR_vol_name":"法上","KR_radical":"冫","KR_vol":"v5","KR_radical_num":42,"Entry":"〓","Def":"「此クタリ二水ノトコロニアリ」　フチ(LH)","KRID_sn":"S15384","KRID":"K05033810"},{"KR2ID":"K0503382","KR_Tenri_p":"Tb039820","KR_vol_name":"法上","KR_radical":"冫","KR_vol":"v5","KR_radical_num":42,"Entry":"减","Def":"俗減字　オトス(LLH)　ヘク(LH\")　ヘス　和ケム","KRID_sn":"S15385","KRID":"K05033820"},{"KR2ID":"K0503383","KR_Tenri_p":"Tb039830","KR_vol_name":"法上","KR_radical":"冫","KR_vol":"v5","KR_radical_num":42,"Entry":"冸","Def":"ソヽク","KRID_sn":"S15386","KRID":"K05033830"},{"KR2ID":"K0503384","KR_Tenri_p":"Tb039840","KR_vol_name":"法上","KR_radical":"冫","KR_vol":"v5","KR_radical_num":42,"Entry":"⿰氵⿰关⺉","Def":"フカシ","KRID_sn":"S15387","KRID":"K05033840"},{"KR2ID":"K0504621","KR_Tenri_p":"Tb052210","KR_vol_name":"法上","KR_radical":"冫","KR_vol":"v5","KR_radical_num":42,"Entry":"⿰冫員","Def":"ホロフ","KRID_sn":"S15824","KRID":"K05046210"},{"KR2ID":"K0504622","KR_Tenri_p":"Tb052220","KR_vol_name":"法上","KR_radical":"冫","KR_vol":"v5","KR_radical_num":42,"Entry":"将","Def":"即良反　マサシ　ヰル　モテ　イクサ　オキテ　オコナフ(H@@@)　トモ　ヤスシ(@@L\"、シ-ム)　タマフ　ヲサム　人トナル　ホシ　ユク　ト(H)　マサニ(LLH)　トス　シテ(LL)　オクル","KRID_sn":"S15825","KRID":"K05046220"},{"KR2ID":"K0504624","KR_Tenri_p":"Tb052240","KR_vol_name":"法上","KR_radical":"冫","KR_vol":"v5","KR_radical_num":42,"Entry":"⿰冫白","Def":"トヽム","KRID_sn":"S15826","KRID":"K05046240"},{"KR2ID":"K0504631","KR_Tenri_p":"Tb052310","KR_vol_name":"法上","KR_radical":"冫","KR_vol":"v5","KR_radical_num":42,"Entry":"⿰冫夕","Def":"サムシ","KRID_sn":"S15827","KRID":"K05046310"},{"KR2ID":"K0504632","KR_Tenri_p":"Tb052320","KR_vol_name":"法上","KR_radical":"冫","KR_vol":"v5","KR_radical_num":42,"Entry":"⿰冫享","Def":"アツシ","KRID_sn":"S15828","KRID":"K05046320"},{"KR2ID":"K0504633","KR_Tenri_p":"Tb052330","KR_vol_name":"法上","KR_radical":"冫","KR_vol":"v5","KR_radical_num":42,"Entry":"収","Def":"コモル　ヲサム　アキナフ","KRID_sn":"S15829","KRID":"K05046330"},{"KR2ID":"K0504634","KR_Tenri_p":"Tb052340","KR_vol_name":"法上","KR_radical":"冫","KR_vol":"v5","KR_radical_num":42,"Entry":"凉","Def":"呂長反　スヽシ(LH\"H)　コホル　サム〈目〉　サムシ　凉上俗下正　サカス(HH\"L)　タスク(LL@)　カナシフ(HH@@)　和リヤウ　","KRID_sn":"S15830","KRID":"K05046340"},{"KR2ID":"K0504642","KR_Tenri_p":"Tb052420","KR_vol_name":"法上","KR_radical":"冫","KR_vol":"v5","KR_radical_num":42,"Entry":"凅","Def":"カハク　サムシ　コトヽヽク","KRID_sn":"S15831","KRID":"K05046420"},{"KR2ID":"K0504643","KR_Tenri_p":"Tb052430","KR_vol_name":"法上","KR_radical":"冫","KR_vol":"v5","KR_radical_num":42,"Entry":"⿰冫⿰僉殳","Def":"ツラヌ","KRID_sn":"S15832","KRID":"K05046430"},{"KR2ID":"K0504644","KR_Tenri_p":"Tb052440","KR_vol_name":"法上","KR_radical":"冫","KR_vol":"v5","KR_radical_num":42,"Entry":"冷","Def":"力鼎反　スヽシ(LH\"@)　スサマシ(LLLH\")　ヒヤヽカナリ　サムシ　サム　サヤカニ　カナフ　コホル　キヨシ　音靈「レイ」","KRID_sn":"S15833","KRID":"K05046440"},{"KR2ID":"K0504652","KR_Tenri_p":"Tb052521","KR_vol_name":"法上","KR_radical":"冫","KR_vol":"v5","KR_radical_num":42,"Entry":"冷","Def":"ヒイスユレル(LHLLHL)","KRID_sn":"S15834","KRID":"K05046521"},{"KR2ID":"K0504652","KR_Tenri_p":"Tb052521","KR_vol_name":"法上","KR_radical":"冫","KR_vol":"v5","KR_radical_num":42,"Entry":"酢","Def":"ヒイスユレル(LHLLHL)","KRID_sn":"S15835","KRID":"K05046522"},{"KR2ID":"K0504653","KR_Tenri_p":"Tb052530","KR_vol_name":"法上","KR_radical":"冫","KR_vol":"v5","KR_radical_num":42,"Entry":"⿰冫尺","Def":"ヤフル","KRID_sn":"S15836","KRID":"K05046530"},{"KR2ID":"K0504654","KR_Tenri_p":"Tb052540","KR_vol_name":"法上","KR_radical":"冫","KR_vol":"v5","KR_radical_num":42,"Entry":"次","Def":"七回(R)反　ツキ　ツイテ(HHH\")　ヤトル　タスク　クタル　ナホ　ナケク　ナラフ　ヒラク　ナミ(HL)　タツ　ヨシ　ツク(HL\")","KRID_sn":"S15837","KRID":"K05046540"},{"KR2ID":"K0504662","KR_Tenri_p":"Tb052620","KR_vol_name":"法上","KR_radical":"冫","KR_vol":"v5","KR_radical_num":42,"Entry":"⿰冫肛","Def":"イタル","KRID_sn":"S15838","KRID":"K05046620"},{"KR2ID":"K0504663","KR_Tenri_p":"Tb052630","KR_vol_name":"法上","KR_radical":"冫","KR_vol":"v5","KR_radical_num":42,"Entry":"况","Def":"俗況字　イハムヤ(HHHH)　ナラフ(HHL\")　ナスラフ　タクラフ(HHHL)　タトヒ　ヨシ　マス　クラフ　イフ(HL)　イラフ(LL@)　タマ物(LL@)　タマフ(LL@)　和クヰヤウ(@@@HN)","KRID_sn":"S15839","KRID":"K05046630"},{"KR2ID":"K0504672","KR_Tenri_p":"Tb052720","KR_vol_name":"法上","KR_radical":"冫","KR_vol":"v5","KR_radical_num":42,"Entry":"⿰冫切","Def":"トシ　スル","KRID_sn":"S15840","KRID":"K05046720"},{"KR2ID":"K0504673","KR_Tenri_p":"Tb052730","KR_vol_name":"法上","KR_radical":"冫","KR_vol":"v5","KR_radical_num":42,"Entry":"准","Def":"ナスラフ(HH\"HL)　ノリ　ヒトシ　ヒラ　[音]準　上通下正","KRID_sn":"S15841","KRID":"K05046730"},{"KR2ID":"K0504674","KR_Tenri_p":"Tb052740","KR_vol_name":"法上","KR_radical":"冫","KR_vol":"v5","KR_radical_num":42,"Entry":"飡","Def":"クラフ　物クフ(LLH)　ナム　ハム　フサク","KRID_sn":"S15842","KRID":"K05046740"},{"KR2ID":"K0504681","KR_Tenri_p":"Tb052810","KR_vol_name":"法上","KR_radical":"冫","KR_vol":"v5","KR_radical_num":42,"Entry":"憑","Def":"タノム　上通下正","KRID_sn":"S15843","KRID":"K05046810"},{"KR2ID":"K0504682","KR_Tenri_p":"Tb052820","KR_vol_name":"法上","KR_radical":"冫","KR_vol":"v5","KR_radical_num":42,"Entry":"凝","Def":"魚陵反　コル(HL)　ヨル　コヽル　コラス　ナル　トヽム(HH\"@)　サタマル(LL\"HL、マ-ム)","KRID_sn":"S15844","KRID":"K05046820"},{"KR2ID":"K0504684","KR_Tenri_p":"Tb052840","KR_vol_name":"法上","KR_radical":"冫","KR_vol":"v5","KR_radical_num":42,"Entry":"𠗦","Def":"タノム(LL@)　ヨリトコロ　サカユ　カク　カクル　アトラフ　ヨル","KRID_sn":"S15845","KRID":"K05046840"},{"KR2ID":"K0504712","KR_Tenri_p":"Tb053120","KR_vol_name":"法上","KR_radical":"冫","KR_vol":"v5","KR_radical_num":42,"Entry":"凄","Def":"サムシ(LHH)　ウソ　ヤヽ　スヽシ(LH\"@)","KRID_sn":"S15846","KRID":"K05047120"},{"KR2ID":"K0504713","KR_Tenri_p":"Tb053130","KR_vol_name":"法上","KR_radical":"冫","KR_vol":"v5","KR_radical_num":42,"Entry":"㓗","Def":"俗絜字　イサキヨシ(HHH\"HH)　キラヽヽシ(LL@@@)　和ケチ","KRID_sn":"S15847","KRID":"K05047130"},{"KR2ID":"K0504714","KR_Tenri_p":"Tb053140","KR_vol_name":"法上","KR_radical":"冫","KR_vol":"v5","KR_radical_num":42,"Entry":"状","Def":"カタチ　サカリナリ","KRID_sn":"S15848","KRID":"K05047140"},{"KR2ID":"K0504721","KR_Tenri_p":"Tb053210","KR_vol_name":"法上","KR_radical":"冫","KR_vol":"v5","KR_radical_num":42,"Entry":"壮","Def":"サカリナリ　カタチ　スカタ　タケシ　カタトル","KRID_sn":"S15849","KRID":"K05047210"},{"KR2ID":"K0504722","KR_Tenri_p":"Tb053220","KR_vol_name":"法上","KR_radical":"冫","KR_vol":"v5","KR_radical_num":42,"Entry":"馮","Def":"溤　上俗下正","KRID_sn":"S15850","KRID":"K05047220"},{"KR2ID":"K0504723","KR_Tenri_p":"Tb053230","KR_vol_name":"法上","KR_radical":"冫","KR_vol":"v5","KR_radical_num":42,"Entry":"⿰冫叐","Def":"（無）","KRID_sn":"S15851","KRID":"K05047230"},{"KR2ID":"K0504724","KR_Tenri_p":"Tb053240","KR_vol_name":"法上","KR_radical":"冫","KR_vol":"v5","KR_radical_num":42,"Entry":"滅","Def":"（無）","KRID_sn":"S15852","KRID":"K05047240"},{"KR2ID":"K0504731","KR_Tenri_p":"Tb053310","KR_vol_name":"法上","KR_radical":"冫","KR_vol":"v5","KR_radical_num":42,"Entry":"𠖹","Def":"下甲反","KRID_sn":"S15853","KRID":"K05047310"},{"KR2ID":"K0504732","KR_Tenri_p":"Tb053320","KR_vol_name":"法上","KR_radical":"冫","KR_vol":"v5","KR_radical_num":42,"Entry":"扠","Def":"初家初嫁二反","KRID_sn":"S15854","KRID":"K05047320"},{"KR2ID":"K0504733","KR_Tenri_p":"Tb053330","KR_vol_name":"法上","KR_radical":"冫","KR_vol":"v5","KR_radical_num":42,"Entry":"〓","Def":"音⿱穴𠦑","KRID_sn":"S15855","KRID":"K05047330"},{"KR2ID":"K0504734","KR_Tenri_p":"Tb053340","KR_vol_name":"法上","KR_radical":"冫","KR_vol":"v5","KR_radical_num":42,"Entry":"⿰冫戮","Def":"アラハス(LLH@)","KRID_sn":"S15856","KRID":"K05047340"}]